{
    "LINK-EUR": [
        {
            "time": "13.12.2020 23:57",
            "open": "10.64866",
            "high": "10.64866",
            "low": "10.64866",
            "close": "10.64928"
        },
        {
            "time": "14.12.2020 00:01",
            "open": "10.64928",
            "high": "10.64928",
            "low": "10.6211",
            "close": "10.6211"
        },
        {
            "time": "14.12.2020 00:02",
            "open": "10.6211",
            "high": "10.62563",
            "low": "10.6211",
            "close": "10.64438"
        },
        {
            "time": "14.12.2020 00:03",
            "open": "10.64438",
            "high": "10.64438",
            "low": "10.64438",
            "close": "10.65774"
        },
        {
            "time": "14.12.2020 00:05",
            "open": "10.65774",
            "high": "10.65774",
            "low": "10.65774",
            "close": "10.70043"
        },
        {
            "time": "14.12.2020 00:08",
            "open": "10.70043",
            "high": "10.70043",
            "low": "10.70043",
            "close": "10.68677"
        },
        {
            "time": "14.12.2020 00:11",
            "open": "10.68677",
            "high": "10.68677",
            "low": "10.68648",
            "close": "10.68376"
        },
        {
            "time": "14.12.2020 00:14",
            "open": "10.68376",
            "high": "10.68698",
            "low": "10.68376",
            "close": "10.68648"
        },
        {
            "time": "14.12.2020 00:15",
            "open": "10.68648",
            "high": "10.68648",
            "low": "10.67572",
            "close": "10.68866"
        },
        {
            "time": "14.12.2020 00:17",
            "open": "10.68866",
            "high": "10.70209",
            "low": "10.68866",
            "close": "10.70844"
        },
        {
            "time": "14.12.2020 00:18",
            "open": "10.70844",
            "high": "10.70844",
            "low": "10.70844",
            "close": "10.7"
        },
        {
            "time": "14.12.2020 00:21",
            "open": "10.7",
            "high": "10.7",
            "low": "10.67638",
            "close": "10.68013"
        },
        {
            "time": "14.12.2020 00:23",
            "open": "10.68013",
            "high": "10.69883",
            "low": "10.68013",
            "close": "10.71279"
        },
        {
            "time": "14.12.2020 00:25",
            "open": "10.71279",
            "high": "10.71798",
            "low": "10.70555",
            "close": "10.70777"
        },
        {
            "time": "14.12.2020 00:28",
            "open": "10.70777",
            "high": "10.70777",
            "low": "10.70777",
            "close": "10.69418"
        },
        {
            "time": "14.12.2020 00:30",
            "open": "10.69418",
            "high": "10.69418",
            "low": "10.69418",
            "close": "10.709"
        },
        {
            "time": "14.12.2020 00:31",
            "open": "10.709",
            "high": "10.709",
            "low": "10.709",
            "close": "10.67048"
        },
        {
            "time": "14.12.2020 00:35",
            "open": "10.67048",
            "high": "10.67048",
            "low": "10.67048",
            "close": "10.65388"
        },
        {
            "time": "14.12.2020 00:36",
            "open": "10.65388",
            "high": "10.65388",
            "low": "10.63067",
            "close": "10.62563"
        },
        {
            "time": "14.12.2020 00:37",
            "open": "10.62563",
            "high": "10.62563",
            "low": "10.62563",
            "close": "10.63307"
        },
        {
            "time": "14.12.2020 00:38",
            "open": "10.63307",
            "high": "10.63307",
            "low": "10.63307",
            "close": "10.62213"
        },
        {
            "time": "14.12.2020 00:40",
            "open": "10.62213",
            "high": "10.62412",
            "low": "10.62213",
            "close": "10.63296"
        },
        {
            "time": "14.12.2020 00:43",
            "open": "10.63296",
            "high": "10.63296",
            "low": "10.63296",
            "close": "10.637"
        },
        {
            "time": "14.12.2020 00:44",
            "open": "10.637",
            "high": "10.637",
            "low": "10.60912",
            "close": "10.62847"
        },
        {
            "time": "14.12.2020 00:46",
            "open": "10.62847",
            "high": "10.63129",
            "low": "10.62847",
            "close": "10.637"
        },
        {
            "time": "14.12.2020 00:47",
            "open": "10.637",
            "high": "10.64692",
            "low": "10.637",
            "close": "10.63501"
        },
        {
            "time": "14.12.2020 00:48",
            "open": "10.63501",
            "high": "10.63501",
            "low": "10.63501",
            "close": "10.63668"
        },
        {
            "time": "14.12.2020 00:49",
            "open": "10.63668",
            "high": "10.63668",
            "low": "10.63668",
            "close": "10.65045"
        },
        {
            "time": "14.12.2020 00:52",
            "open": "10.65045",
            "high": "10.65045",
            "low": "10.64998",
            "close": "10.65"
        },
        {
            "time": "14.12.2020 00:55",
            "open": "10.65",
            "high": "10.65",
            "low": "10.65",
            "close": "10.65552"
        },
        {
            "time": "14.12.2020 01:00",
            "open": "10.65552",
            "high": "10.65552",
            "low": "10.65552",
            "close": "10.63638"
        },
        {
            "time": "14.12.2020 01:01",
            "open": "10.63638",
            "high": "10.63638",
            "low": "10.63638",
            "close": "10.63331"
        },
        {
            "time": "14.12.2020 01:02",
            "open": "10.63331",
            "high": "10.63894",
            "low": "10.63331",
            "close": "10.66393"
        },
        {
            "time": "14.12.2020 01:05",
            "open": "10.66393",
            "high": "10.66393",
            "low": "10.66069",
            "close": "10.6"
        },
        {
            "time": "14.12.2020 01:07",
            "open": "10.6",
            "high": "10.6",
            "low": "10.5898",
            "close": "10.60488"
        },
        {
            "time": "14.12.2020 01:15",
            "open": "10.60488",
            "high": "10.60488",
            "low": "10.60488",
            "close": "10.59849"
        },
        {
            "time": "14.12.2020 01:17",
            "open": "10.59849",
            "high": "10.59849",
            "low": "10.59849",
            "close": "10.59167"
        },
        {
            "time": "14.12.2020 01:20",
            "open": "10.59167",
            "high": "10.59167",
            "low": "10.57944",
            "close": "10.59724"
        },
        {
            "time": "14.12.2020 01:21",
            "open": "10.59724",
            "high": "10.59724",
            "low": "10.59724",
            "close": "10.61966"
        },
        {
            "time": "14.12.2020 01:24",
            "open": "10.61966",
            "high": "10.61966",
            "low": "10.61966",
            "close": "10.59883"
        },
        {
            "time": "14.12.2020 01:29",
            "open": "10.59883",
            "high": "10.59883",
            "low": "10.59883",
            "close": "10.58357"
        },
        {
            "time": "14.12.2020 01:31",
            "open": "10.58357",
            "high": "10.58357",
            "low": "10.58357",
            "close": "10.60102"
        },
        {
            "time": "14.12.2020 01:33",
            "open": "10.60102",
            "high": "10.60284",
            "low": "10.60102",
            "close": "10.58893"
        },
        {
            "time": "14.12.2020 01:35",
            "open": "10.58893",
            "high": "10.58893",
            "low": "10.58893",
            "close": "10.58907"
        },
        {
            "time": "14.12.2020 01:37",
            "open": "10.58907",
            "high": "10.58907",
            "low": "10.58907",
            "close": "10.5764"
        },
        {
            "time": "14.12.2020 01:38",
            "open": "10.5764",
            "high": "10.5764",
            "low": "10.5764",
            "close": "10.60045"
        },
        {
            "time": "14.12.2020 01:43",
            "open": "10.60045",
            "high": "10.60045",
            "low": "10.60045",
            "close": "10.56329"
        },
        {
            "time": "14.12.2020 01:45",
            "open": "10.56329",
            "high": "10.5648",
            "low": "10.56329",
            "close": "10.55"
        },
        {
            "time": "14.12.2020 01:46",
            "open": "10.55",
            "high": "10.55",
            "low": "10.51804",
            "close": "10.52677"
        },
        {
            "time": "14.12.2020 01:47",
            "open": "10.52677",
            "high": "10.53549",
            "low": "10.51739",
            "close": "10.51133"
        },
        {
            "time": "14.12.2020 01:48",
            "open": "10.51133",
            "high": "10.51133",
            "low": "10.4834",
            "close": "10.50826"
        },
        {
            "time": "14.12.2020 01:49",
            "open": "10.50826",
            "high": "10.5251",
            "low": "10.50575",
            "close": "10.52758"
        },
        {
            "time": "14.12.2020 01:50",
            "open": "10.52758",
            "high": "10.52758",
            "low": "10.49512",
            "close": "10.51543"
        },
        {
            "time": "14.12.2020 01:52",
            "open": "10.51543",
            "high": "10.51543",
            "low": "10.51543",
            "close": "10.5251"
        },
        {
            "time": "14.12.2020 01:53",
            "open": "10.5251",
            "high": "10.5251",
            "low": "10.52311",
            "close": "10.50563"
        },
        {
            "time": "14.12.2020 01:54",
            "open": "10.50563",
            "high": "10.50563",
            "low": "10.50563",
            "close": "10.5251"
        },
        {
            "time": "14.12.2020 01:55",
            "open": "10.5251",
            "high": "10.5251",
            "low": "10.5251",
            "close": "10.5152"
        },
        {
            "time": "14.12.2020 02:00",
            "open": "10.5152",
            "high": "10.5152",
            "low": "10.5152",
            "close": "10.5462"
        },
        {
            "time": "14.12.2020 02:15",
            "open": "10.5462",
            "high": "10.5462",
            "low": "10.5462",
            "close": "10.53679"
        },
        {
            "time": "14.12.2020 02:24",
            "open": "10.53679",
            "high": "10.53679",
            "low": "10.51993",
            "close": "10.54277"
        },
        {
            "time": "14.12.2020 02:25",
            "open": "10.54277",
            "high": "10.54277",
            "low": "10.54115",
            "close": "10.53841"
        },
        {
            "time": "14.12.2020 02:31",
            "open": "10.53841",
            "high": "10.53841",
            "low": "10.53841",
            "close": "10.54247"
        },
        {
            "time": "14.12.2020 02:41",
            "open": "10.54247",
            "high": "10.54247",
            "low": "10.54247",
            "close": "10.54236"
        },
        {
            "time": "14.12.2020 02:43",
            "open": "10.54236",
            "high": "10.54236",
            "low": "10.54236",
            "close": "10.51955"
        },
        {
            "time": "14.12.2020 02:55",
            "open": "10.51955",
            "high": "10.51955",
            "low": "10.51955",
            "close": "10.48257"
        },
        {
            "time": "14.12.2020 03:03",
            "open": "10.48257",
            "high": "10.48257",
            "low": "10.48257",
            "close": "10.52435"
        },
        {
            "time": "14.12.2020 03:07",
            "open": "10.52435",
            "high": "10.52686",
            "low": "10.52435",
            "close": "10.52596"
        },
        {
            "time": "14.12.2020 03:09",
            "open": "10.52596",
            "high": "10.53126",
            "low": "10.52596",
            "close": "10.53022"
        },
        {
            "time": "14.12.2020 03:10",
            "open": "10.53022",
            "high": "10.53022",
            "low": "10.53022",
            "close": "10.52471"
        },
        {
            "time": "14.12.2020 03:22",
            "open": "10.52471",
            "high": "10.53874",
            "low": "10.52471",
            "close": "10.55321"
        },
        {
            "time": "14.12.2020 03:27",
            "open": "10.55321",
            "high": "10.55321",
            "low": "10.55321",
            "close": "10.56304"
        },
        {
            "time": "14.12.2020 03:28",
            "open": "10.56304",
            "high": "10.56304",
            "low": "10.56304",
            "close": "10.58285"
        },
        {
            "time": "14.12.2020 03:39",
            "open": "10.58285",
            "high": "10.58754",
            "low": "10.58285",
            "close": "10.58606"
        },
        {
            "time": "14.12.2020 03:40",
            "open": "10.58606",
            "high": "10.58606",
            "low": "10.58606",
            "close": "10.64209"
        },
        {
            "time": "14.12.2020 04:04",
            "open": "10.64209",
            "high": "10.6421",
            "low": "10.64209",
            "close": "10.66769"
        },
        {
            "time": "14.12.2020 04:08",
            "open": "10.66769",
            "high": "10.66769",
            "low": "10.66769",
            "close": "10.66049"
        },
        {
            "time": "14.12.2020 04:16",
            "open": "10.66049",
            "high": "10.66049",
            "low": "10.657",
            "close": "10.66274"
        },
        {
            "time": "14.12.2020 04:17",
            "open": "10.66274",
            "high": "10.66299",
            "low": "10.66274",
            "close": "10.63519"
        },
        {
            "time": "14.12.2020 04:23",
            "open": "10.63519",
            "high": "10.6352",
            "low": "10.63519",
            "close": "10.635"
        },
        {
            "time": "14.12.2020 04:39",
            "open": "10.635",
            "high": "10.635",
            "low": "10.635",
            "close": "10.62326"
        },
        {
            "time": "14.12.2020 04:43",
            "open": "10.62326",
            "high": "10.62326",
            "low": "10.62326",
            "close": "10.62113"
        },
        {
            "time": "14.12.2020 04:48",
            "open": "10.62113",
            "high": "10.62113",
            "low": "10.62113",
            "close": "10.61956"
        },
        {
            "time": "14.12.2020 04:59",
            "open": "10.61956",
            "high": "10.61959",
            "low": "10.61956",
            "close": "10.56655"
        },
        {
            "time": "14.12.2020 05:18",
            "open": "10.56655",
            "high": "10.56719",
            "low": "10.56655",
            "close": "10.51912"
        },
        {
            "time": "14.12.2020 05:21",
            "open": "10.51912",
            "high": "10.51912",
            "low": "10.49682",
            "close": "10.47057"
        },
        {
            "time": "14.12.2020 05:27",
            "open": "10.47057",
            "high": "10.47057",
            "low": "10.457",
            "close": "10.44266"
        },
        {
            "time": "14.12.2020 05:36",
            "open": "10.44266",
            "high": "10.44266",
            "low": "10.43067",
            "close": "10.44"
        },
        {
            "time": "14.12.2020 05:37",
            "open": "10.44",
            "high": "10.44345",
            "low": "10.44",
            "close": "10.4275"
        },
        {
            "time": "14.12.2020 05:50",
            "open": "10.4275",
            "high": "10.4275",
            "low": "10.4275",
            "close": "10.42705"
        },
        {
            "time": "14.12.2020 05:56",
            "open": "10.42705",
            "high": "10.42705",
            "low": "10.42705",
            "close": "10.42229"
        },
        {
            "time": "14.12.2020 06:02",
            "open": "10.42229",
            "high": "10.42229",
            "low": "10.42229",
            "close": "10.41712"
        },
        {
            "time": "14.12.2020 06:07",
            "open": "10.41712",
            "high": "10.41712",
            "low": "10.41712",
            "close": "10.40709"
        },
        {
            "time": "14.12.2020 06:17",
            "open": "10.40709",
            "high": "10.40709",
            "low": "10.4",
            "close": "10.41914"
        },
        {
            "time": "14.12.2020 06:18",
            "open": "10.41914",
            "high": "10.41914",
            "low": "10.41914",
            "close": "10.42245"
        },
        {
            "time": "14.12.2020 06:19",
            "open": "10.42245",
            "high": "10.42855",
            "low": "10.42245",
            "close": "10.42176"
        },
        {
            "time": "14.12.2020 06:21",
            "open": "10.42176",
            "high": "10.42177",
            "low": "10.42176",
            "close": "10.45283"
        },
        {
            "time": "14.12.2020 06:27",
            "open": "10.45283",
            "high": "10.45283",
            "low": "10.44662",
            "close": "10.45"
        },
        {
            "time": "14.12.2020 06:38",
            "open": "10.45",
            "high": "10.45",
            "low": "10.45",
            "close": "10.4453"
        },
        {
            "time": "14.12.2020 06:39",
            "open": "10.4453",
            "high": "10.4453",
            "low": "10.4453",
            "close": "10.43715"
        },
        {
            "time": "14.12.2020 06:51",
            "open": "10.43715",
            "high": "10.43715",
            "low": "10.43715",
            "close": "10.41718"
        },
        {
            "time": "14.12.2020 07:01",
            "open": "10.41718",
            "high": "10.43715",
            "low": "10.41718",
            "close": "10.45865"
        },
        {
            "time": "14.12.2020 07:05",
            "open": "10.45865",
            "high": "10.45865",
            "low": "10.45865",
            "close": "10.46998"
        },
        {
            "time": "14.12.2020 07:07",
            "open": "10.46998",
            "high": "10.46998",
            "low": "10.46998",
            "close": "10.47537"
        },
        {
            "time": "14.12.2020 07:08",
            "open": "10.47537",
            "high": "10.48191",
            "low": "10.47537",
            "close": "10.44943"
        },
        {
            "time": "14.12.2020 07:11",
            "open": "10.44943",
            "high": "10.44943",
            "low": "10.44871",
            "close": "10.4741"
        },
        {
            "time": "14.12.2020 07:16",
            "open": "10.4741",
            "high": "10.4741",
            "low": "10.4741",
            "close": "10.46578"
        },
        {
            "time": "14.12.2020 07:18",
            "open": "10.46578",
            "high": "10.46578",
            "low": "10.46578",
            "close": "10.45994"
        },
        {
            "time": "14.12.2020 07:19",
            "open": "10.45994",
            "high": "10.45994",
            "low": "10.45994",
            "close": "10.48068"
        },
        {
            "time": "14.12.2020 07:21",
            "open": "10.48068",
            "high": "10.48068",
            "low": "10.48068",
            "close": "10.47872"
        },
        {
            "time": "14.12.2020 07:22",
            "open": "10.47872",
            "high": "10.47872",
            "low": "10.47872",
            "close": "10.4717"
        },
        {
            "time": "14.12.2020 07:24",
            "open": "10.4717",
            "high": "10.4717",
            "low": "10.4717",
            "close": "10.48529"
        },
        {
            "time": "14.12.2020 07:26",
            "open": "10.48529",
            "high": "10.48529",
            "low": "10.48529",
            "close": "10.46312"
        },
        {
            "time": "14.12.2020 07:30",
            "open": "10.46312",
            "high": "10.46312",
            "low": "10.46312",
            "close": "10.45711"
        },
        {
            "time": "14.12.2020 07:33",
            "open": "10.45711",
            "high": "10.45711",
            "low": "10.45711",
            "close": "10.45929"
        },
        {
            "time": "14.12.2020 07:34",
            "open": "10.45929",
            "high": "10.45929",
            "low": "10.45929",
            "close": "10.47216"
        },
        {
            "time": "14.12.2020 07:38",
            "open": "10.47216",
            "high": "10.47216",
            "low": "10.47216",
            "close": "10.46547"
        },
        {
            "time": "14.12.2020 07:40",
            "open": "10.46547",
            "high": "10.46547",
            "low": "10.46522",
            "close": "10.47322"
        },
        {
            "time": "14.12.2020 07:45",
            "open": "10.47322",
            "high": "10.47322",
            "low": "10.47322",
            "close": "10.47346"
        },
        {
            "time": "14.12.2020 07:46",
            "open": "10.47346",
            "high": "10.47346",
            "low": "10.47346",
            "close": "10.482"
        },
        {
            "time": "14.12.2020 07:51",
            "open": "10.482",
            "high": "10.482",
            "low": "10.47974",
            "close": "10.48"
        },
        {
            "time": "14.12.2020 07:56",
            "open": "10.48",
            "high": "10.48",
            "low": "10.48",
            "close": "10.48"
        },
        {
            "time": "14.12.2020 07:57",
            "open": "10.48",
            "high": "10.49037",
            "low": "10.48",
            "close": "10.50462"
        },
        {
            "time": "14.12.2020 07:58",
            "open": "10.50462",
            "high": "10.50462",
            "low": "10.50462",
            "close": "10.45206"
        },
        {
            "time": "14.12.2020 08:08",
            "open": "10.45206",
            "high": "10.45206",
            "low": "10.45206",
            "close": "10.45524"
        },
        {
            "time": "14.12.2020 08:11",
            "open": "10.45524",
            "high": "10.45695",
            "low": "10.4552",
            "close": "10.44057"
        },
        {
            "time": "14.12.2020 08:15",
            "open": "10.44057",
            "high": "10.4419",
            "low": "10.44057",
            "close": "10.43824"
        },
        {
            "time": "14.12.2020 08:16",
            "open": "10.43824",
            "high": "10.43824",
            "low": "10.43824",
            "close": "10.44002"
        },
        {
            "time": "14.12.2020 08:17",
            "open": "10.44002",
            "high": "10.44002",
            "low": "10.44002",
            "close": "10.429"
        },
        {
            "time": "14.12.2020 08:20",
            "open": "10.429",
            "high": "10.429",
            "low": "10.429",
            "close": "10.46233"
        },
        {
            "time": "14.12.2020 08:27",
            "open": "10.46233",
            "high": "10.46233",
            "low": "10.46233",
            "close": "10.47454"
        },
        {
            "time": "14.12.2020 08:29",
            "open": "10.47454",
            "high": "10.47454",
            "low": "10.47454",
            "close": "10.46519"
        },
        {
            "time": "14.12.2020 08:30",
            "open": "10.46519",
            "high": "10.47453",
            "low": "10.46519",
            "close": "10.48184"
        },
        {
            "time": "14.12.2020 08:34",
            "open": "10.48184",
            "high": "10.48184",
            "low": "10.47453",
            "close": "10.48503"
        },
        {
            "time": "14.12.2020 08:37",
            "open": "10.48503",
            "high": "10.48503",
            "low": "10.48503",
            "close": "10.47453"
        },
        {
            "time": "14.12.2020 08:38",
            "open": "10.47453",
            "high": "10.47453",
            "low": "10.47453",
            "close": "10.49488"
        },
        {
            "time": "14.12.2020 08:43",
            "open": "10.49488",
            "high": "10.49538",
            "low": "10.49488",
            "close": "10.49503"
        },
        {
            "time": "14.12.2020 08:45",
            "open": "10.49503",
            "high": "10.49503",
            "low": "10.49503",
            "close": "10.48886"
        },
        {
            "time": "14.12.2020 08:50",
            "open": "10.48886",
            "high": "10.48886",
            "low": "10.48162",
            "close": "10.47014"
        },
        {
            "time": "14.12.2020 08:51",
            "open": "10.47014",
            "high": "10.48162",
            "low": "10.47014",
            "close": "10.46594"
        },
        {
            "time": "14.12.2020 08:53",
            "open": "10.46594",
            "high": "10.46594",
            "low": "10.46594",
            "close": "10.46228"
        },
        {
            "time": "14.12.2020 08:54",
            "open": "10.46228",
            "high": "10.46228",
            "low": "10.46228",
            "close": "10.44607"
        },
        {
            "time": "14.12.2020 08:57",
            "open": "10.44607",
            "high": "10.44607",
            "low": "10.44352",
            "close": "10.43081"
        },
        {
            "time": "14.12.2020 09:00",
            "open": "10.43081",
            "high": "10.43081",
            "low": "10.43081",
            "close": "10.44601"
        },
        {
            "time": "14.12.2020 09:01",
            "open": "10.44601",
            "high": "10.44601",
            "low": "10.44601",
            "close": "10.45341"
        },
        {
            "time": "14.12.2020 09:05",
            "open": "10.45341",
            "high": "10.45341",
            "low": "10.45341",
            "close": "10.46351"
        },
        {
            "time": "14.12.2020 09:10",
            "open": "10.46351",
            "high": "10.46351",
            "low": "10.46351",
            "close": "10.47598"
        },
        {
            "time": "14.12.2020 09:11",
            "open": "10.47598",
            "high": "10.47598",
            "low": "10.47598",
            "close": "10.48565"
        },
        {
            "time": "14.12.2020 09:18",
            "open": "10.48565",
            "high": "10.49663",
            "low": "10.48565",
            "close": "10.48577"
        },
        {
            "time": "14.12.2020 09:19",
            "open": "10.48577",
            "high": "10.48577",
            "low": "10.48561",
            "close": "10.49652"
        },
        {
            "time": "14.12.2020 09:20",
            "open": "10.49652",
            "high": "10.497",
            "low": "10.46545",
            "close": "10.47038"
        },
        {
            "time": "14.12.2020 09:21",
            "open": "10.47038",
            "high": "10.47038",
            "low": "10.47038",
            "close": "10.45003"
        },
        {
            "time": "14.12.2020 09:23",
            "open": "10.45003",
            "high": "10.45003",
            "low": "10.45003",
            "close": "10.45104"
        },
        {
            "time": "14.12.2020 09:27",
            "open": "10.45104",
            "high": "10.45104",
            "low": "10.45104",
            "close": "10.44053"
        },
        {
            "time": "14.12.2020 09:30",
            "open": "10.44053",
            "high": "10.44053",
            "low": "10.44053",
            "close": "10.45469"
        },
        {
            "time": "14.12.2020 09:32",
            "open": "10.45469",
            "high": "10.45469",
            "low": "10.45469",
            "close": "10.46067"
        },
        {
            "time": "14.12.2020 09:35",
            "open": "10.46067",
            "high": "10.46067",
            "low": "10.44326",
            "close": "10.46433"
        },
        {
            "time": "14.12.2020 09:40",
            "open": "10.46433",
            "high": "10.46435",
            "low": "10.46433",
            "close": "10.4649"
        },
        {
            "time": "14.12.2020 09:43",
            "open": "10.4649",
            "high": "10.4649",
            "low": "10.46489",
            "close": "10.4636"
        },
        {
            "time": "14.12.2020 09:45",
            "open": "10.4636",
            "high": "10.4636",
            "low": "10.4636",
            "close": "10.47796"
        },
        {
            "time": "14.12.2020 09:50",
            "open": "10.47796",
            "high": "10.47796",
            "low": "10.47796",
            "close": "10.478"
        },
        {
            "time": "14.12.2020 09:52",
            "open": "10.478",
            "high": "10.478",
            "low": "10.478",
            "close": "10.4908"
        },
        {
            "time": "14.12.2020 09:54",
            "open": "10.4908",
            "high": "10.4908",
            "low": "10.4908",
            "close": "10.49269"
        },
        {
            "time": "14.12.2020 09:57",
            "open": "10.49269",
            "high": "10.4927",
            "low": "10.49269",
            "close": "10.47563"
        },
        {
            "time": "14.12.2020 09:58",
            "open": "10.47563",
            "high": "10.47563",
            "low": "10.47563",
            "close": "10.48826"
        },
        {
            "time": "14.12.2020 09:59",
            "open": "10.48826",
            "high": "10.48826",
            "low": "10.48826",
            "close": "10.48678"
        },
        {
            "time": "14.12.2020 10:04",
            "open": "10.48678",
            "high": "10.48902",
            "low": "10.48678",
            "close": "10.49507"
        },
        {
            "time": "14.12.2020 10:12",
            "open": "10.49507",
            "high": "10.49507",
            "low": "10.49507",
            "close": "10.44362"
        },
        {
            "time": "14.12.2020 10:19",
            "open": "10.44362",
            "high": "10.44362",
            "low": "10.44362",
            "close": "10.44617"
        },
        {
            "time": "14.12.2020 10:20",
            "open": "10.44617",
            "high": "10.44617",
            "low": "10.44616",
            "close": "10.44797"
        },
        {
            "time": "14.12.2020 10:21",
            "open": "10.44797",
            "high": "10.44797",
            "low": "10.44797",
            "close": "10.44639"
        },
        {
            "time": "14.12.2020 10:22",
            "open": "10.44639",
            "high": "10.44639",
            "low": "10.44639",
            "close": "10.45239"
        },
        {
            "time": "14.12.2020 10:24",
            "open": "10.45239",
            "high": "10.45239",
            "low": "10.45239",
            "close": "10.43469"
        },
        {
            "time": "14.12.2020 10:25",
            "open": "10.43469",
            "high": "10.45289",
            "low": "10.43469",
            "close": "10.45289"
        },
        {
            "time": "14.12.2020 10:29",
            "open": "10.45289",
            "high": "10.45289",
            "low": "10.45289",
            "close": "10.45588"
        },
        {
            "time": "14.12.2020 10:31",
            "open": "10.45588",
            "high": "10.45588",
            "low": "10.45588",
            "close": "10.4551"
        },
        {
            "time": "14.12.2020 10:33",
            "open": "10.4551",
            "high": "10.4551",
            "low": "10.4551",
            "close": "10.45603"
        },
        {
            "time": "14.12.2020 10:34",
            "open": "10.45603",
            "high": "10.45603",
            "low": "10.45603",
            "close": "10.5101"
        },
        {
            "time": "14.12.2020 10:36",
            "open": "10.5101",
            "high": "10.5101",
            "low": "10.5101",
            "close": "10.50716"
        },
        {
            "time": "14.12.2020 10:37",
            "open": "10.50716",
            "high": "10.50801",
            "low": "10.50716",
            "close": "10.5051"
        },
        {
            "time": "14.12.2020 10:38",
            "open": "10.5051",
            "high": "10.50645",
            "low": "10.5051",
            "close": "10.50215"
        },
        {
            "time": "14.12.2020 10:39",
            "open": "10.50215",
            "high": "10.50262",
            "low": "10.50215",
            "close": "10.49442"
        },
        {
            "time": "14.12.2020 10:40",
            "open": "10.49442",
            "high": "10.49443",
            "low": "10.49192",
            "close": "10.47376"
        },
        {
            "time": "14.12.2020 10:48",
            "open": "10.47376",
            "high": "10.47376",
            "low": "10.47376",
            "close": "10.47395"
        },
        {
            "time": "14.12.2020 10:50",
            "open": "10.47395",
            "high": "10.47395",
            "low": "10.47395",
            "close": "10.47406"
        },
        {
            "time": "14.12.2020 10:51",
            "open": "10.47406",
            "high": "10.47406",
            "low": "10.47406",
            "close": "10.47411"
        },
        {
            "time": "14.12.2020 10:53",
            "open": "10.47411",
            "high": "10.47784",
            "low": "10.47411",
            "close": "10.47411"
        },
        {
            "time": "14.12.2020 10:54",
            "open": "10.47411",
            "high": "10.47411",
            "low": "10.47411",
            "close": "10.47427"
        },
        {
            "time": "14.12.2020 10:58",
            "open": "10.47427",
            "high": "10.47448",
            "low": "10.47427",
            "close": "10.49562"
        },
        {
            "time": "14.12.2020 11:00",
            "open": "10.49562",
            "high": "10.49562",
            "low": "10.49305",
            "close": "10.46792"
        },
        {
            "time": "14.12.2020 11:01",
            "open": "10.46792",
            "high": "10.46792",
            "low": "10.46792",
            "close": "10.49121"
        },
        {
            "time": "14.12.2020 11:10",
            "open": "10.49121",
            "high": "10.50796",
            "low": "10.49121",
            "close": "10.51742"
        },
        {
            "time": "14.12.2020 11:13",
            "open": "10.51742",
            "high": "10.51802",
            "low": "10.51742",
            "close": "10.4912"
        },
        {
            "time": "14.12.2020 11:15",
            "open": "10.4912",
            "high": "10.4912",
            "low": "10.49049",
            "close": "10.47882"
        },
        {
            "time": "14.12.2020 11:19",
            "open": "10.47882",
            "high": "10.47882",
            "low": "10.45914",
            "close": "10.48303"
        },
        {
            "time": "14.12.2020 11:26",
            "open": "10.48303",
            "high": "10.48591",
            "low": "10.47276",
            "close": "10.48182"
        },
        {
            "time": "14.12.2020 11:27",
            "open": "10.48182",
            "high": "10.48182",
            "low": "10.48182",
            "close": "10.4737"
        },
        {
            "time": "14.12.2020 11:30",
            "open": "10.4737",
            "high": "10.4737",
            "low": "10.4737",
            "close": "10.50116"
        },
        {
            "time": "14.12.2020 11:32",
            "open": "10.50116",
            "high": "10.50514",
            "low": "10.50116",
            "close": "10.45538"
        },
        {
            "time": "14.12.2020 11:38",
            "open": "10.45538",
            "high": "10.45538",
            "low": "10.45537",
            "close": "10.46587"
        },
        {
            "time": "14.12.2020 11:39",
            "open": "10.46587",
            "high": "10.46587",
            "low": "10.46587",
            "close": "10.42"
        },
        {
            "time": "14.12.2020 11:43",
            "open": "10.42",
            "high": "10.42",
            "low": "10.42",
            "close": "10.41627"
        },
        {
            "time": "14.12.2020 11:45",
            "open": "10.41627",
            "high": "10.41627",
            "low": "10.41627",
            "close": "10.40925"
        },
        {
            "time": "14.12.2020 11:46",
            "open": "10.40925",
            "high": "10.40925",
            "low": "10.4",
            "close": "10.39"
        },
        {
            "time": "14.12.2020 11:47",
            "open": "10.39",
            "high": "10.39",
            "low": "10.39",
            "close": "10.3737"
        },
        {
            "time": "14.12.2020 11:48",
            "open": "10.3737",
            "high": "10.3737",
            "low": "10.35",
            "close": "10.36418"
        },
        {
            "time": "14.12.2020 11:49",
            "open": "10.36418",
            "high": "10.36418",
            "low": "10.34734",
            "close": "10.35069"
        },
        {
            "time": "14.12.2020 11:50",
            "open": "10.35069",
            "high": "10.36733",
            "low": "10.32238",
            "close": "10.33686"
        },
        {
            "time": "14.12.2020 11:51",
            "open": "10.33686",
            "high": "10.33686",
            "low": "10.33269",
            "close": "10.33635"
        },
        {
            "time": "14.12.2020 11:52",
            "open": "10.33635",
            "high": "10.33635",
            "low": "10.33635",
            "close": "10.33269"
        },
        {
            "time": "14.12.2020 11:53",
            "open": "10.33269",
            "high": "10.34729",
            "low": "10.33269",
            "close": "10.35783"
        },
        {
            "time": "14.12.2020 11:54",
            "open": "10.35783",
            "high": "10.35783",
            "low": "10.34192",
            "close": "10.34651"
        },
        {
            "time": "14.12.2020 11:55",
            "open": "10.34651",
            "high": "10.34651",
            "low": "10.34651",
            "close": "10.35689"
        },
        {
            "time": "14.12.2020 11:57",
            "open": "10.35689",
            "high": "10.35689",
            "low": "10.35689",
            "close": "10.3482"
        },
        {
            "time": "14.12.2020 11:58",
            "open": "10.3482",
            "high": "10.3482",
            "low": "10.3482",
            "close": "10.33393"
        },
        {
            "time": "14.12.2020 11:59",
            "open": "10.33393",
            "high": "10.33393",
            "low": "10.33393",
            "close": "10.3224"
        },
        {
            "time": "14.12.2020 12:00",
            "open": "10.3224",
            "high": "10.33119",
            "low": "10.3224",
            "close": "10.35032"
        },
        {
            "time": "14.12.2020 12:01",
            "open": "10.35032",
            "high": "10.35032",
            "low": "10.35032",
            "close": "10.31915"
        },
        {
            "time": "14.12.2020 12:05",
            "open": "10.31915",
            "high": "10.31915",
            "low": "10.29903",
            "close": "10.28"
        },
        {
            "time": "14.12.2020 12:09",
            "open": "10.28",
            "high": "10.28",
            "low": "10.22169",
            "close": "10.22976"
        },
        {
            "time": "14.12.2020 12:10",
            "open": "10.22976",
            "high": "10.24108",
            "low": "10.22233",
            "close": "10.25118"
        },
        {
            "time": "14.12.2020 12:12",
            "open": "10.25118",
            "high": "10.25118",
            "low": "10.25118",
            "close": "10.23202"
        },
        {
            "time": "14.12.2020 12:13",
            "open": "10.23202",
            "high": "10.23202",
            "low": "10.23202",
            "close": "10.24267"
        },
        {
            "time": "14.12.2020 12:14",
            "open": "10.24267",
            "high": "10.24269",
            "low": "10.24267",
            "close": "10.26437"
        },
        {
            "time": "14.12.2020 12:15",
            "open": "10.26437",
            "high": "10.26437",
            "low": "10.26437",
            "close": "10.27534"
        },
        {
            "time": "14.12.2020 12:16",
            "open": "10.27534",
            "high": "10.27534",
            "low": "10.27534",
            "close": "10.27539"
        },
        {
            "time": "14.12.2020 12:18",
            "open": "10.27539",
            "high": "10.27539",
            "low": "10.27539",
            "close": "10.2665"
        },
        {
            "time": "14.12.2020 12:19",
            "open": "10.2665",
            "high": "10.27289",
            "low": "10.2665",
            "close": "10.28"
        },
        {
            "time": "14.12.2020 12:24",
            "open": "10.28",
            "high": "10.28",
            "low": "10.28",
            "close": "10.2741"
        },
        {
            "time": "14.12.2020 12:25",
            "open": "10.2741",
            "high": "10.2741",
            "low": "10.2741",
            "close": "10.2741"
        },
        {
            "time": "14.12.2020 12:26",
            "open": "10.2741",
            "high": "10.2741",
            "low": "10.26632",
            "close": "10.25193"
        },
        {
            "time": "14.12.2020 12:30",
            "open": "10.25193",
            "high": "10.25193",
            "low": "10.2519",
            "close": "10.27834"
        },
        {
            "time": "14.12.2020 12:32",
            "open": "10.27834",
            "high": "10.27834",
            "low": "10.27834",
            "close": "10.28289"
        },
        {
            "time": "14.12.2020 12:33",
            "open": "10.28289",
            "high": "10.28316",
            "low": "10.28228",
            "close": "10.26868"
        },
        {
            "time": "14.12.2020 12:34",
            "open": "10.26868",
            "high": "10.26868",
            "low": "10.26868",
            "close": "10.26254"
        },
        {
            "time": "14.12.2020 12:35",
            "open": "10.26254",
            "high": "10.26254",
            "low": "10.26254",
            "close": "10.28054"
        },
        {
            "time": "14.12.2020 12:37",
            "open": "10.28054",
            "high": "10.28054",
            "low": "10.28054",
            "close": "10.28054"
        },
        {
            "time": "14.12.2020 12:39",
            "open": "10.28054",
            "high": "10.28352",
            "low": "10.28054",
            "close": "10.27319"
        },
        {
            "time": "14.12.2020 12:41",
            "open": "10.27319",
            "high": "10.27319",
            "low": "10.27319",
            "close": "10.25647"
        },
        {
            "time": "14.12.2020 12:42",
            "open": "10.25647",
            "high": "10.25654",
            "low": "10.25647",
            "close": "10.24696"
        },
        {
            "time": "14.12.2020 12:44",
            "open": "10.24696",
            "high": "10.24696",
            "low": "10.24696",
            "close": "10.25025"
        },
        {
            "time": "14.12.2020 12:45",
            "open": "10.25025",
            "high": "10.25025",
            "low": "10.24571",
            "close": "10.25546"
        },
        {
            "time": "14.12.2020 12:47",
            "open": "10.25546",
            "high": "10.27013",
            "low": "10.25546",
            "close": "10.26749"
        },
        {
            "time": "14.12.2020 12:48",
            "open": "10.26749",
            "high": "10.26749",
            "low": "10.25526",
            "close": "10.28231"
        },
        {
            "time": "14.12.2020 12:50",
            "open": "10.28231",
            "high": "10.28231",
            "low": "10.28231",
            "close": "10.25974"
        },
        {
            "time": "14.12.2020 12:51",
            "open": "10.25974",
            "high": "10.25974",
            "low": "10.25971",
            "close": "10.26809"
        },
        {
            "time": "14.12.2020 12:53",
            "open": "10.26809",
            "high": "10.26809",
            "low": "10.26809",
            "close": "10.25874"
        },
        {
            "time": "14.12.2020 12:54",
            "open": "10.25874",
            "high": "10.25874",
            "low": "10.2579",
            "close": "10.25479"
        },
        {
            "time": "14.12.2020 12:56",
            "open": "10.25479",
            "high": "10.25479",
            "low": "10.24949",
            "close": "10.24806"
        },
        {
            "time": "14.12.2020 12:58",
            "open": "10.24806",
            "high": "10.24806",
            "low": "10.24806",
            "close": "10.23833"
        },
        {
            "time": "14.12.2020 12:59",
            "open": "10.23833",
            "high": "10.26235",
            "low": "10.23833",
            "close": "10.25423"
        },
        {
            "time": "14.12.2020 13:00",
            "open": "10.25423",
            "high": "10.2599",
            "low": "10.25386",
            "close": "10.31103"
        },
        {
            "time": "14.12.2020 13:04",
            "open": "10.31103",
            "high": "10.31103",
            "low": "10.29848",
            "close": "10.3076"
        },
        {
            "time": "14.12.2020 13:05",
            "open": "10.3076",
            "high": "10.3076",
            "low": "10.3076",
            "close": "10.30547"
        },
        {
            "time": "14.12.2020 13:08",
            "open": "10.30547",
            "high": "10.30547",
            "low": "10.30547",
            "close": "10.26053"
        },
        {
            "time": "14.12.2020 13:14",
            "open": "10.26053",
            "high": "10.26053",
            "low": "10.26053",
            "close": "10.25634"
        },
        {
            "time": "14.12.2020 13:15",
            "open": "10.25634",
            "high": "10.25634",
            "low": "10.25634",
            "close": "10.25384"
        },
        {
            "time": "14.12.2020 13:16",
            "open": "10.25384",
            "high": "10.25384",
            "low": "10.25384",
            "close": "10.23475"
        },
        {
            "time": "14.12.2020 13:18",
            "open": "10.23475",
            "high": "10.23752",
            "low": "10.21712",
            "close": "10.21057"
        },
        {
            "time": "14.12.2020 13:19",
            "open": "10.21057",
            "high": "10.2183",
            "low": "10.21057",
            "close": "10.21057"
        },
        {
            "time": "14.12.2020 13:20",
            "open": "10.21057",
            "high": "10.22603",
            "low": "10.20556",
            "close": "10.21112"
        },
        {
            "time": "14.12.2020 13:21",
            "open": "10.21112",
            "high": "10.21112",
            "low": "10.20817",
            "close": "10.21802"
        },
        {
            "time": "14.12.2020 13:23",
            "open": "10.21802",
            "high": "10.21802",
            "low": "10.2133",
            "close": "10.2253"
        },
        {
            "time": "14.12.2020 13:26",
            "open": "10.2253",
            "high": "10.23844",
            "low": "10.22",
            "close": "10.28188"
        },
        {
            "time": "14.12.2020 13:28",
            "open": "10.28188",
            "high": "10.28236",
            "low": "10.28188",
            "close": "10.26747"
        },
        {
            "time": "14.12.2020 13:29",
            "open": "10.26747",
            "high": "10.26747",
            "low": "10.26747",
            "close": "10.27908"
        },
        {
            "time": "14.12.2020 13:31",
            "open": "10.27908",
            "high": "10.2849",
            "low": "10.27908",
            "close": "10.28056"
        },
        {
            "time": "14.12.2020 13:33",
            "open": "10.28056",
            "high": "10.28056",
            "low": "10.24249",
            "close": "10.24558"
        },
        {
            "time": "14.12.2020 13:34",
            "open": "10.24558",
            "high": "10.24558",
            "low": "10.24558",
            "close": "10.24777"
        },
        {
            "time": "14.12.2020 13:35",
            "open": "10.24777",
            "high": "10.24837",
            "low": "10.23659",
            "close": "10.24031"
        },
        {
            "time": "14.12.2020 13:36",
            "open": "10.24031",
            "high": "10.24031",
            "low": "10.24031",
            "close": "10.2444"
        },
        {
            "time": "14.12.2020 13:46",
            "open": "10.2444",
            "high": "10.2444",
            "low": "10.2444",
            "close": "10.24994"
        },
        {
            "time": "14.12.2020 13:47",
            "open": "10.24994",
            "high": "10.24994",
            "low": "10.24994",
            "close": "10.2488"
        },
        {
            "time": "14.12.2020 13:48",
            "open": "10.2488",
            "high": "10.2488",
            "low": "10.2488",
            "close": "10.21944"
        },
        {
            "time": "14.12.2020 13:51",
            "open": "10.21944",
            "high": "10.22894",
            "low": "10.21756",
            "close": "10.21932"
        },
        {
            "time": "14.12.2020 13:53",
            "open": "10.21932",
            "high": "10.22144",
            "low": "10.20462",
            "close": "10.22143"
        },
        {
            "time": "14.12.2020 13:54",
            "open": "10.22143",
            "high": "10.22143",
            "low": "10.22143",
            "close": "10.22143"
        },
        {
            "time": "14.12.2020 13:55",
            "open": "10.22143",
            "high": "10.2221",
            "low": "10.22143",
            "close": "10.23025"
        },
        {
            "time": "14.12.2020 13:57",
            "open": "10.23025",
            "high": "10.23025",
            "low": "10.21839",
            "close": "10.25192"
        },
        {
            "time": "14.12.2020 13:59",
            "open": "10.25192",
            "high": "10.25192",
            "low": "10.25192",
            "close": "10.24289"
        },
        {
            "time": "14.12.2020 14:00",
            "open": "10.24289",
            "high": "10.24289",
            "low": "10.24289",
            "close": "10.26426"
        },
        {
            "time": "14.12.2020 14:01",
            "open": "10.26426",
            "high": "10.26426",
            "low": "10.26426",
            "close": "10.27063"
        },
        {
            "time": "14.12.2020 14:04",
            "open": "10.27063",
            "high": "10.27181",
            "low": "10.27063",
            "close": "10.2575"
        },
        {
            "time": "14.12.2020 14:05",
            "open": "10.2575",
            "high": "10.2575",
            "low": "10.25731",
            "close": "10.25372"
        },
        {
            "time": "14.12.2020 14:06",
            "open": "10.25372",
            "high": "10.25372",
            "low": "10.25371",
            "close": "10.24979"
        },
        {
            "time": "14.12.2020 14:08",
            "open": "10.24979",
            "high": "10.25008",
            "low": "10.24979",
            "close": "10.2557"
        },
        {
            "time": "14.12.2020 14:09",
            "open": "10.2557",
            "high": "10.2557",
            "low": "10.24394",
            "close": "10.24019"
        },
        {
            "time": "14.12.2020 14:13",
            "open": "10.24019",
            "high": "10.24019",
            "low": "10.23548",
            "close": "10.21781"
        },
        {
            "time": "14.12.2020 14:15",
            "open": "10.21781",
            "high": "10.21781",
            "low": "10.21781",
            "close": "10.21"
        },
        {
            "time": "14.12.2020 14:16",
            "open": "10.21",
            "high": "10.21377",
            "low": "10.2055",
            "close": "10.20772"
        },
        {
            "time": "14.12.2020 14:17",
            "open": "10.20772",
            "high": "10.2165",
            "low": "10.20584",
            "close": "10.21171"
        },
        {
            "time": "14.12.2020 14:20",
            "open": "10.21171",
            "high": "10.21171",
            "low": "10.21171",
            "close": "10.20001"
        },
        {
            "time": "14.12.2020 14:21",
            "open": "10.20001",
            "high": "10.20001",
            "low": "10.15",
            "close": "10.15972"
        },
        {
            "time": "14.12.2020 14:22",
            "open": "10.15972",
            "high": "10.15972",
            "low": "10.15972",
            "close": "10.15734"
        },
        {
            "time": "14.12.2020 14:23",
            "open": "10.15734",
            "high": "10.16602",
            "low": "10.1172",
            "close": "10.16927"
        },
        {
            "time": "14.12.2020 14:24",
            "open": "10.16927",
            "high": "10.16983",
            "low": "10.16927",
            "close": "10.18256"
        },
        {
            "time": "14.12.2020 14:25",
            "open": "10.18256",
            "high": "10.18256",
            "low": "10.18256",
            "close": "10.18618"
        },
        {
            "time": "14.12.2020 14:26",
            "open": "10.18618",
            "high": "10.18618",
            "low": "10.18618",
            "close": "10.17408"
        },
        {
            "time": "14.12.2020 14:27",
            "open": "10.17408",
            "high": "10.17408",
            "low": "10.17408",
            "close": "10.18346"
        },
        {
            "time": "14.12.2020 14:28",
            "open": "10.18346",
            "high": "10.20212",
            "low": "10.18346",
            "close": "10.19098"
        },
        {
            "time": "14.12.2020 14:29",
            "open": "10.19098",
            "high": "10.19098",
            "low": "10.18506",
            "close": "10.18506"
        },
        {
            "time": "14.12.2020 14:30",
            "open": "10.18506",
            "high": "10.18506",
            "low": "10.18506",
            "close": "10.18491"
        },
        {
            "time": "14.12.2020 14:31",
            "open": "10.18491",
            "high": "10.18492",
            "low": "10.17667",
            "close": "10.20219"
        },
        {
            "time": "14.12.2020 14:34",
            "open": "10.20219",
            "high": "10.20219",
            "low": "10.18996",
            "close": "10.20961"
        }
    ]
}