{
    "ZRX-EUR": [
        {
            "time": "25.12.2020 23:55",
            "open": "0.292",
            "high": "0.292",
            "low": "0.292",
            "close": "0.292254"
        },
        {
            "time": "26.12.2020 00:06",
            "open": "0.292254",
            "high": "0.292254",
            "low": "0.292254",
            "close": "0.291664"
        },
        {
            "time": "26.12.2020 00:08",
            "open": "0.291664",
            "high": "0.291664",
            "low": "0.291664",
            "close": "0.29218"
        },
        {
            "time": "26.12.2020 00:10",
            "open": "0.29218",
            "high": "0.29218",
            "low": "0.29218",
            "close": "0.291"
        },
        {
            "time": "26.12.2020 00:14",
            "open": "0.291",
            "high": "0.291",
            "low": "0.291",
            "close": "0.290545"
        },
        {
            "time": "26.12.2020 00:15",
            "open": "0.290545",
            "high": "0.291616",
            "low": "0.290545",
            "close": "0.291423"
        },
        {
            "time": "26.12.2020 00:16",
            "open": "0.291423",
            "high": "0.291425",
            "low": "0.291391",
            "close": "0.290887"
        },
        {
            "time": "26.12.2020 00:18",
            "open": "0.290887",
            "high": "0.290887",
            "low": "0.290887",
            "close": "0.294384"
        },
        {
            "time": "26.12.2020 00:34",
            "open": "0.294384",
            "high": "0.294384",
            "low": "0.294384",
            "close": "0.294071"
        },
        {
            "time": "26.12.2020 00:41",
            "open": "0.294071",
            "high": "0.294071",
            "low": "0.294071",
            "close": "0.294677"
        },
        {
            "time": "26.12.2020 00:45",
            "open": "0.294677",
            "high": "0.294677",
            "low": "0.294677",
            "close": "0.294158"
        },
        {
            "time": "26.12.2020 00:48",
            "open": "0.294158",
            "high": "0.294158",
            "low": "0.294158",
            "close": "0.29458"
        },
        {
            "time": "26.12.2020 00:50",
            "open": "0.29458",
            "high": "0.29458",
            "low": "0.293496",
            "close": "0.293471"
        },
        {
            "time": "26.12.2020 00:55",
            "open": "0.293471",
            "high": "0.293471",
            "low": "0.293471",
            "close": "0.293433"
        },
        {
            "time": "26.12.2020 01:04",
            "open": "0.293433",
            "high": "0.293433",
            "low": "0.293433",
            "close": "0.292245"
        },
        {
            "time": "26.12.2020 01:05",
            "open": "0.292245",
            "high": "0.292245",
            "low": "0.292245",
            "close": "0.294225"
        },
        {
            "time": "26.12.2020 01:23",
            "open": "0.294225",
            "high": "0.294225",
            "low": "0.294225",
            "close": "0.292845"
        },
        {
            "time": "26.12.2020 01:24",
            "open": "0.292845",
            "high": "0.292845",
            "low": "0.292845",
            "close": "0.293743"
        },
        {
            "time": "26.12.2020 01:25",
            "open": "0.293743",
            "high": "0.293743",
            "low": "0.293743",
            "close": "0.294426"
        },
        {
            "time": "26.12.2020 01:31",
            "open": "0.294426",
            "high": "0.294426",
            "low": "0.294426",
            "close": "0.294532"
        },
        {
            "time": "26.12.2020 01:41",
            "open": "0.294532",
            "high": "0.294532",
            "low": "0.294532",
            "close": "0.294384"
        },
        {
            "time": "26.12.2020 01:52",
            "open": "0.294384",
            "high": "0.294384",
            "low": "0.294384",
            "close": "0.294273"
        },
        {
            "time": "26.12.2020 01:54",
            "open": "0.294273",
            "high": "0.294273",
            "low": "0.294273",
            "close": "0.294153"
        },
        {
            "time": "26.12.2020 02:00",
            "open": "0.294153",
            "high": "0.294153",
            "low": "0.294153",
            "close": "0.294625"
        },
        {
            "time": "26.12.2020 02:07",
            "open": "0.294625",
            "high": "0.294625",
            "low": "0.294625",
            "close": "0.293478"
        },
        {
            "time": "26.12.2020 02:08",
            "open": "0.293478",
            "high": "0.293478",
            "low": "0.293478",
            "close": "0.294718"
        },
        {
            "time": "26.12.2020 02:26",
            "open": "0.294718",
            "high": "0.294718",
            "low": "0.294718",
            "close": "0.295057"
        },
        {
            "time": "26.12.2020 02:38",
            "open": "0.295057",
            "high": "0.295057",
            "low": "0.295057",
            "close": "0.293909"
        },
        {
            "time": "26.12.2020 02:40",
            "open": "0.293909",
            "high": "0.293909",
            "low": "0.293478",
            "close": "0.293478"
        },
        {
            "time": "26.12.2020 02:41",
            "open": "0.293478",
            "high": "0.293853",
            "low": "0.293478",
            "close": "0.293478"
        },
        {
            "time": "26.12.2020 02:42",
            "open": "0.293478",
            "high": "0.293478",
            "low": "0.293478",
            "close": "0.29348"
        },
        {
            "time": "26.12.2020 02:45",
            "open": "0.29348",
            "high": "0.29348",
            "low": "0.29348",
            "close": "0.293499"
        },
        {
            "time": "26.12.2020 02:48",
            "open": "0.293499",
            "high": "0.293499",
            "low": "0.293499",
            "close": "0.293493"
        },
        {
            "time": "26.12.2020 02:50",
            "open": "0.293493",
            "high": "0.293493",
            "low": "0.293493",
            "close": "0.293491"
        },
        {
            "time": "26.12.2020 02:52",
            "open": "0.293491",
            "high": "0.293491",
            "low": "0.293478",
            "close": "0.293479"
        },
        {
            "time": "26.12.2020 02:53",
            "open": "0.293479",
            "high": "0.293479",
            "low": "0.293478",
            "close": "0.293478"
        },
        {
            "time": "26.12.2020 02:58",
            "open": "0.293478",
            "high": "0.293478",
            "low": "0.293478",
            "close": "0.293478"
        },
        {
            "time": "26.12.2020 02:59",
            "open": "0.293478",
            "high": "0.293478",
            "low": "0.293478",
            "close": "0.29348"
        },
        {
            "time": "26.12.2020 03:01",
            "open": "0.29348",
            "high": "0.29348",
            "low": "0.293478",
            "close": "0.293478"
        },
        {
            "time": "26.12.2020 03:03",
            "open": "0.293478",
            "high": "0.293478",
            "low": "0.293478",
            "close": "0.293478"
        },
        {
            "time": "26.12.2020 03:04",
            "open": "0.293478",
            "high": "0.293478",
            "low": "0.293478",
            "close": "0.293478"
        },
        {
            "time": "26.12.2020 03:21",
            "open": "0.293478",
            "high": "0.293478",
            "low": "0.293478",
            "close": "0.293785"
        },
        {
            "time": "26.12.2020 03:22",
            "open": "0.293785",
            "high": "0.293785",
            "low": "0.293478",
            "close": "0.293478"
        },
        {
            "time": "26.12.2020 03:24",
            "open": "0.293478",
            "high": "0.293478",
            "low": "0.293478",
            "close": "0.293853"
        },
        {
            "time": "26.12.2020 03:31",
            "open": "0.293853",
            "high": "0.293861",
            "low": "0.293853",
            "close": "0.293482"
        },
        {
            "time": "26.12.2020 03:37",
            "open": "0.293482",
            "high": "0.293482",
            "low": "0.293479",
            "close": "0.293872"
        },
        {
            "time": "26.12.2020 03:38",
            "open": "0.293872",
            "high": "0.293872",
            "low": "0.293872",
            "close": "0.293479"
        },
        {
            "time": "26.12.2020 03:40",
            "open": "0.293479",
            "high": "0.293479",
            "low": "0.293479",
            "close": "0.293479"
        },
        {
            "time": "26.12.2020 03:41",
            "open": "0.293479",
            "high": "0.293479",
            "low": "0.293479",
            "close": "0.293479"
        },
        {
            "time": "26.12.2020 03:44",
            "open": "0.293479",
            "high": "0.293479",
            "low": "0.293479",
            "close": "0.293478"
        },
        {
            "time": "26.12.2020 03:45",
            "open": "0.293478",
            "high": "0.293478",
            "low": "0.293478",
            "close": "0.293675"
        },
        {
            "time": "26.12.2020 03:47",
            "open": "0.293675",
            "high": "0.293675",
            "low": "0.293675",
            "close": "0.296926"
        },
        {
            "time": "26.12.2020 04:53",
            "open": "0.296926",
            "high": "0.296926",
            "low": "0.296926",
            "close": "0.298324"
        },
        {
            "time": "26.12.2020 05:03",
            "open": "0.298324",
            "high": "0.298798",
            "low": "0.298324",
            "close": "0.299497"
        },
        {
            "time": "26.12.2020 05:07",
            "open": "0.299497",
            "high": "0.299497",
            "low": "0.299497",
            "close": "0.299497"
        },
        {
            "time": "26.12.2020 05:09",
            "open": "0.299497",
            "high": "0.3",
            "low": "0.299497",
            "close": "0.299415"
        },
        {
            "time": "26.12.2020 05:14",
            "open": "0.299415",
            "high": "0.299415",
            "low": "0.299415",
            "close": "0.3"
        },
        {
            "time": "26.12.2020 05:20",
            "open": "0.3",
            "high": "0.3",
            "low": "0.3",
            "close": "0.30078"
        },
        {
            "time": "26.12.2020 05:46",
            "open": "0.30078",
            "high": "0.30092",
            "low": "0.30078",
            "close": "0.30092"
        },
        {
            "time": "26.12.2020 05:48",
            "open": "0.30092",
            "high": "0.30092",
            "low": "0.30036",
            "close": "0.299419"
        },
        {
            "time": "26.12.2020 06:01",
            "open": "0.299419",
            "high": "0.299419",
            "low": "0.299417",
            "close": "0.299966"
        },
        {
            "time": "26.12.2020 06:06",
            "open": "0.299966",
            "high": "0.299966",
            "low": "0.299966",
            "close": "0.299415"
        },
        {
            "time": "26.12.2020 06:12",
            "open": "0.299415",
            "high": "0.299415",
            "low": "0.299415",
            "close": "0.299415"
        },
        {
            "time": "26.12.2020 06:13",
            "open": "0.299415",
            "high": "0.299415",
            "low": "0.299415",
            "close": "0.298035"
        },
        {
            "time": "26.12.2020 06:36",
            "open": "0.298035",
            "high": "0.298035",
            "low": "0.298035",
            "close": "0.299427"
        },
        {
            "time": "26.12.2020 06:50",
            "open": "0.299427",
            "high": "0.299427",
            "low": "0.299427",
            "close": "0.296808"
        },
        {
            "time": "26.12.2020 07:15",
            "open": "0.296808",
            "high": "0.296808",
            "low": "0.296808",
            "close": "0.296"
        },
        {
            "time": "26.12.2020 07:31",
            "open": "0.296",
            "high": "0.296672",
            "low": "0.296",
            "close": "0.296"
        },
        {
            "time": "26.12.2020 07:32",
            "open": "0.296",
            "high": "0.296004",
            "low": "0.296",
            "close": "0.296"
        },
        {
            "time": "26.12.2020 07:33",
            "open": "0.296",
            "high": "0.296",
            "low": "0.295491",
            "close": "0.296182"
        },
        {
            "time": "26.12.2020 07:36",
            "open": "0.296182",
            "high": "0.296184",
            "low": "0.296182",
            "close": "0.296205"
        },
        {
            "time": "26.12.2020 07:42",
            "open": "0.296205",
            "high": "0.296205",
            "low": "0.296205",
            "close": "0.296205"
        },
        {
            "time": "26.12.2020 07:52",
            "open": "0.296205",
            "high": "0.296456",
            "low": "0.296205",
            "close": "0.298097"
        },
        {
            "time": "26.12.2020 08:06",
            "open": "0.298097",
            "high": "0.298097",
            "low": "0.298097",
            "close": "0.296292"
        },
        {
            "time": "26.12.2020 08:08",
            "open": "0.296292",
            "high": "0.296292",
            "low": "0.296264",
            "close": "0.296784"
        },
        {
            "time": "26.12.2020 08:16",
            "open": "0.296784",
            "high": "0.296784",
            "low": "0.296784",
            "close": "0.297668"
        },
        {
            "time": "26.12.2020 08:18",
            "open": "0.297668",
            "high": "0.297668",
            "low": "0.297668",
            "close": "0.297406"
        },
        {
            "time": "26.12.2020 08:26",
            "open": "0.297406",
            "high": "0.297408",
            "low": "0.297406",
            "close": "0.296513"
        },
        {
            "time": "26.12.2020 08:31",
            "open": "0.296513",
            "high": "0.296513",
            "low": "0.296513",
            "close": "0.296508"
        },
        {
            "time": "26.12.2020 08:38",
            "open": "0.296508",
            "high": "0.296508",
            "low": "0.296508",
            "close": "0.295021"
        },
        {
            "time": "26.12.2020 08:48",
            "open": "0.295021",
            "high": "0.295021",
            "low": "0.295019",
            "close": "0.294144"
        },
        {
            "time": "26.12.2020 08:54",
            "open": "0.294144",
            "high": "0.294492",
            "low": "0.294144",
            "close": "0.296339"
        },
        {
            "time": "26.12.2020 08:57",
            "open": "0.296339",
            "high": "0.296339",
            "low": "0.296339",
            "close": "0.297198"
        },
        {
            "time": "26.12.2020 08:59",
            "open": "0.297198",
            "high": "0.2972",
            "low": "0.297198",
            "close": "0.297746"
        },
        {
            "time": "26.12.2020 09:03",
            "open": "0.297746",
            "high": "0.297746",
            "low": "0.297746",
            "close": "0.297746"
        },
        {
            "time": "26.12.2020 09:05",
            "open": "0.297746",
            "high": "0.297746",
            "low": "0.297746",
            "close": "0.299929"
        },
        {
            "time": "26.12.2020 09:07",
            "open": "0.299929",
            "high": "0.299929",
            "low": "0.299929",
            "close": "0.300738"
        },
        {
            "time": "26.12.2020 09:15",
            "open": "0.300738",
            "high": "0.300738",
            "low": "0.300738",
            "close": "0.300334"
        },
        {
            "time": "26.12.2020 09:25",
            "open": "0.300334",
            "high": "0.300334",
            "low": "0.300334",
            "close": "0.300437"
        },
        {
            "time": "26.12.2020 09:28",
            "open": "0.300437",
            "high": "0.300437",
            "low": "0.300437",
            "close": "0.299516"
        },
        {
            "time": "26.12.2020 09:40",
            "open": "0.299516",
            "high": "0.299516",
            "low": "0.299516",
            "close": "0.299516"
        },
        {
            "time": "26.12.2020 09:45",
            "open": "0.299516",
            "high": "0.299516",
            "low": "0.299334",
            "close": "0.299516"
        },
        {
            "time": "26.12.2020 09:46",
            "open": "0.299516",
            "high": "0.299516",
            "low": "0.29943",
            "close": "0.299516"
        },
        {
            "time": "26.12.2020 09:48",
            "open": "0.299516",
            "high": "0.299516",
            "low": "0.299516",
            "close": "0.299051"
        },
        {
            "time": "26.12.2020 09:49",
            "open": "0.299051",
            "high": "0.299516",
            "low": "0.299051",
            "close": "0.299516"
        },
        {
            "time": "26.12.2020 09:52",
            "open": "0.299516",
            "high": "0.299516",
            "low": "0.29934",
            "close": "0.299183"
        },
        {
            "time": "26.12.2020 10:04",
            "open": "0.299183",
            "high": "0.299183",
            "low": "0.299183",
            "close": "0.299515"
        },
        {
            "time": "26.12.2020 10:07",
            "open": "0.299515",
            "high": "0.299515",
            "low": "0.29918",
            "close": "0.29918"
        },
        {
            "time": "26.12.2020 10:19",
            "open": "0.29918",
            "high": "0.29918",
            "low": "0.298183",
            "close": "0.29818"
        },
        {
            "time": "26.12.2020 10:22",
            "open": "0.29818",
            "high": "0.29818",
            "low": "0.29818",
            "close": "0.29818"
        },
        {
            "time": "26.12.2020 10:26",
            "open": "0.29818",
            "high": "0.29818",
            "low": "0.297745",
            "close": "0.295661"
        },
        {
            "time": "26.12.2020 10:37",
            "open": "0.295661",
            "high": "0.295661",
            "low": "0.295661",
            "close": "0.295644"
        },
        {
            "time": "26.12.2020 10:39",
            "open": "0.295644",
            "high": "0.295644",
            "low": "0.295644",
            "close": "0.295665"
        },
        {
            "time": "26.12.2020 10:40",
            "open": "0.295665",
            "high": "0.295665",
            "low": "0.295665",
            "close": "0.296067"
        },
        {
            "time": "26.12.2020 10:41",
            "open": "0.296067",
            "high": "0.296067",
            "low": "0.296067",
            "close": "0.296427"
        },
        {
            "time": "26.12.2020 10:57",
            "open": "0.296427",
            "high": "0.296427",
            "low": "0.296427",
            "close": "0.296315"
        },
        {
            "time": "26.12.2020 11:01",
            "open": "0.296315",
            "high": "0.296315",
            "low": "0.295691",
            "close": "0.295984"
        },
        {
            "time": "26.12.2020 11:19",
            "open": "0.295984",
            "high": "0.295984",
            "low": "0.295984",
            "close": "0.294748"
        },
        {
            "time": "26.12.2020 11:23",
            "open": "0.294748",
            "high": "0.294748",
            "low": "0.294516",
            "close": "0.295526"
        },
        {
            "time": "26.12.2020 11:24",
            "open": "0.295526",
            "high": "0.295526",
            "low": "0.295526",
            "close": "0.295804"
        },
        {
            "time": "26.12.2020 11:25",
            "open": "0.295804",
            "high": "0.295804",
            "low": "0.295804",
            "close": "0.293915"
        },
        {
            "time": "26.12.2020 11:36",
            "open": "0.293915",
            "high": "0.293915",
            "low": "0.293697",
            "close": "0.293699"
        },
        {
            "time": "26.12.2020 11:37",
            "open": "0.293699",
            "high": "0.293699",
            "low": "0.293699",
            "close": "0.293"
        },
        {
            "time": "26.12.2020 11:40",
            "open": "0.293",
            "high": "0.293",
            "low": "0.293",
            "close": "0.293098"
        },
        {
            "time": "26.12.2020 11:42",
            "open": "0.293098",
            "high": "0.293098",
            "low": "0.292",
            "close": "0.291626"
        },
        {
            "time": "26.12.2020 11:43",
            "open": "0.291626",
            "high": "0.291626",
            "low": "0.291626",
            "close": "0.292995"
        },
        {
            "time": "26.12.2020 11:53",
            "open": "0.292995",
            "high": "0.292995",
            "low": "0.292995",
            "close": "0.292995"
        },
        {
            "time": "26.12.2020 11:54",
            "open": "0.292995",
            "high": "0.292995",
            "low": "0.292995",
            "close": "0.292995"
        },
        {
            "time": "26.12.2020 11:58",
            "open": "0.292995",
            "high": "0.292995",
            "low": "0.292995",
            "close": "0.292646"
        },
        {
            "time": "26.12.2020 11:59",
            "open": "0.292646",
            "high": "0.292646",
            "low": "0.292646",
            "close": "0.292924"
        },
        {
            "time": "26.12.2020 12:02",
            "open": "0.292924",
            "high": "0.292924",
            "low": "0.292924",
            "close": "0.292807"
        },
        {
            "time": "26.12.2020 12:03",
            "open": "0.292807",
            "high": "0.292807",
            "low": "0.292807",
            "close": "0.292995"
        },
        {
            "time": "26.12.2020 12:07",
            "open": "0.292995",
            "high": "0.292995",
            "low": "0.292995",
            "close": "0.292872"
        },
        {
            "time": "26.12.2020 12:08",
            "open": "0.292872",
            "high": "0.292872",
            "low": "0.292872",
            "close": "0.292995"
        },
        {
            "time": "26.12.2020 12:09",
            "open": "0.292995",
            "high": "0.292995",
            "low": "0.292693",
            "close": "0.292994"
        },
        {
            "time": "26.12.2020 12:10",
            "open": "0.292994",
            "high": "0.292994",
            "low": "0.292609",
            "close": "0.292993"
        },
        {
            "time": "26.12.2020 12:11",
            "open": "0.292993",
            "high": "0.292993",
            "low": "0.292993",
            "close": "0.292525"
        },
        {
            "time": "26.12.2020 12:15",
            "open": "0.292525",
            "high": "0.292525",
            "low": "0.291713",
            "close": "0.291"
        },
        {
            "time": "26.12.2020 12:17",
            "open": "0.291",
            "high": "0.291",
            "low": "0.29072",
            "close": "0.290309"
        },
        {
            "time": "26.12.2020 12:19",
            "open": "0.290309",
            "high": "0.290309",
            "low": "0.290309",
            "close": "0.291511"
        },
        {
            "time": "26.12.2020 12:22",
            "open": "0.291511",
            "high": "0.291511",
            "low": "0.291511",
            "close": "0.290069"
        },
        {
            "time": "26.12.2020 12:23",
            "open": "0.290069",
            "high": "0.290069",
            "low": "0.290066",
            "close": "0.291501"
        },
        {
            "time": "26.12.2020 12:26",
            "open": "0.291501",
            "high": "0.291501",
            "low": "0.291501",
            "close": "0.292993"
        },
        {
            "time": "26.12.2020 12:28",
            "open": "0.292993",
            "high": "0.292993",
            "low": "0.292993",
            "close": "0.292929"
        },
        {
            "time": "26.12.2020 12:29",
            "open": "0.292929",
            "high": "0.292929",
            "low": "0.292929",
            "close": "0.291915"
        },
        {
            "time": "26.12.2020 12:30",
            "open": "0.291915",
            "high": "0.291915",
            "low": "0.291915",
            "close": "0.292993"
        },
        {
            "time": "26.12.2020 12:33",
            "open": "0.292993",
            "high": "0.292993",
            "low": "0.292993",
            "close": "0.293316"
        },
        {
            "time": "26.12.2020 12:35",
            "open": "0.293316",
            "high": "0.293316",
            "low": "0.293316",
            "close": "0.294577"
        },
        {
            "time": "26.12.2020 12:37",
            "open": "0.294577",
            "high": "0.294577",
            "low": "0.294577",
            "close": "0.293281"
        },
        {
            "time": "26.12.2020 12:42",
            "open": "0.293281",
            "high": "0.293281",
            "low": "0.293281",
            "close": "0.296977"
        },
        {
            "time": "26.12.2020 12:43",
            "open": "0.296977",
            "high": "0.296977",
            "low": "0.296977",
            "close": "0.294207"
        },
        {
            "time": "26.12.2020 13:00",
            "open": "0.294207",
            "high": "0.294207",
            "low": "0.294207",
            "close": "0.294207"
        },
        {
            "time": "26.12.2020 13:08",
            "open": "0.294207",
            "high": "0.294207",
            "low": "0.294207",
            "close": "0.294207"
        },
        {
            "time": "26.12.2020 13:13",
            "open": "0.294207",
            "high": "0.294207",
            "low": "0.294207",
            "close": "0.293226"
        },
        {
            "time": "26.12.2020 13:16",
            "open": "0.293226",
            "high": "0.293226",
            "low": "0.293226",
            "close": "0.292839"
        },
        {
            "time": "26.12.2020 13:19",
            "open": "0.292839",
            "high": "0.292839",
            "low": "0.292839",
            "close": "0.291598"
        },
        {
            "time": "26.12.2020 13:40",
            "open": "0.291598",
            "high": "0.291598",
            "low": "0.291598",
            "close": "0.291766"
        },
        {
            "time": "26.12.2020 13:45",
            "open": "0.291766",
            "high": "0.291766",
            "low": "0.291766",
            "close": "0.293437"
        },
        {
            "time": "26.12.2020 13:48",
            "open": "0.293437",
            "high": "0.293635",
            "low": "0.293437",
            "close": "0.293137"
        },
        {
            "time": "26.12.2020 13:51",
            "open": "0.293137",
            "high": "0.293137",
            "low": "0.293137",
            "close": "0.293636"
        },
        {
            "time": "26.12.2020 13:52",
            "open": "0.293636",
            "high": "0.294177",
            "low": "0.293636",
            "close": "0.293616"
        },
        {
            "time": "26.12.2020 13:54",
            "open": "0.293616",
            "high": "0.293616",
            "low": "0.293616",
            "close": "0.294207"
        },
        {
            "time": "26.12.2020 13:57",
            "open": "0.294207",
            "high": "0.294231",
            "low": "0.294207",
            "close": "0.292404"
        },
        {
            "time": "26.12.2020 14:19",
            "open": "0.292404",
            "high": "0.292404",
            "low": "0.292404",
            "close": "0.292062"
        },
        {
            "time": "26.12.2020 14:23",
            "open": "0.292062",
            "high": "0.292062",
            "low": "0.292062",
            "close": "0.292266"
        },
        {
            "time": "26.12.2020 14:26",
            "open": "0.292266",
            "high": "0.292266",
            "low": "0.292266",
            "close": "0.29"
        },
        {
            "time": "26.12.2020 14:32",
            "open": "0.29",
            "high": "0.29",
            "low": "0.289781",
            "close": "0.289781"
        },
        {
            "time": "26.12.2020 14:34",
            "open": "0.289781",
            "high": "0.289781",
            "low": "0.289647",
            "close": "0.29011"
        },
        {
            "time": "26.12.2020 14:41",
            "open": "0.29011",
            "high": "0.29011",
            "low": "0.29011",
            "close": "0.289647"
        },
        {
            "time": "26.12.2020 14:42",
            "open": "0.289647",
            "high": "0.289647",
            "low": "0.289307",
            "close": "0.289307"
        },
        {
            "time": "26.12.2020 14:45",
            "open": "0.289307",
            "high": "0.289307",
            "low": "0.289307",
            "close": "0.29036"
        },
        {
            "time": "26.12.2020 14:50",
            "open": "0.29036",
            "high": "0.290362",
            "low": "0.29036",
            "close": "0.289546"
        },
        {
            "time": "26.12.2020 14:52",
            "open": "0.289546",
            "high": "0.289546",
            "low": "0.289546",
            "close": "0.289976"
        },
        {
            "time": "26.12.2020 14:54",
            "open": "0.289976",
            "high": "0.289976",
            "low": "0.289976",
            "close": "0.290096"
        },
        {
            "time": "26.12.2020 15:01",
            "open": "0.290096",
            "high": "0.290097",
            "low": "0.289196",
            "close": "0.289"
        },
        {
            "time": "26.12.2020 15:03",
            "open": "0.289",
            "high": "0.289358",
            "low": "0.289",
            "close": "0.288896"
        },
        {
            "time": "26.12.2020 15:06",
            "open": "0.288896",
            "high": "0.288896",
            "low": "0.288896",
            "close": "0.289256"
        },
        {
            "time": "26.12.2020 15:07",
            "open": "0.289256",
            "high": "0.289256",
            "low": "0.289256",
            "close": "0.290363"
        },
        {
            "time": "26.12.2020 15:11",
            "open": "0.290363",
            "high": "0.290363",
            "low": "0.290363",
            "close": "0.290363"
        },
        {
            "time": "26.12.2020 15:12",
            "open": "0.290363",
            "high": "0.290363",
            "low": "0.290363",
            "close": "0.29168"
        },
        {
            "time": "26.12.2020 15:17",
            "open": "0.29168",
            "high": "0.29168",
            "low": "0.29168",
            "close": "0.290312"
        },
        {
            "time": "26.12.2020 15:18",
            "open": "0.290312",
            "high": "0.290312",
            "low": "0.290312",
            "close": "0.290312"
        },
        {
            "time": "26.12.2020 15:19",
            "open": "0.290312",
            "high": "0.290312",
            "low": "0.290312",
            "close": "0.2899"
        },
        {
            "time": "26.12.2020 15:32",
            "open": "0.2899",
            "high": "0.2899",
            "low": "0.288965",
            "close": "0.289734"
        },
        {
            "time": "26.12.2020 15:33",
            "open": "0.289734",
            "high": "0.289734",
            "low": "0.289734",
            "close": "0.2893"
        },
        {
            "time": "26.12.2020 15:36",
            "open": "0.2893",
            "high": "0.2893",
            "low": "0.2893",
            "close": "0.289924"
        },
        {
            "time": "26.12.2020 15:42",
            "open": "0.289924",
            "high": "0.289924",
            "low": "0.289924",
            "close": "0.289922"
        },
        {
            "time": "26.12.2020 15:46",
            "open": "0.289922",
            "high": "0.289922",
            "low": "0.289922",
            "close": "0.289754"
        },
        {
            "time": "26.12.2020 15:47",
            "open": "0.289754",
            "high": "0.289754",
            "low": "0.289754",
            "close": "0.289375"
        },
        {
            "time": "26.12.2020 15:52",
            "open": "0.289375",
            "high": "0.289375",
            "low": "0.289193",
            "close": "0.289414"
        },
        {
            "time": "26.12.2020 15:53",
            "open": "0.289414",
            "high": "0.289414",
            "low": "0.289414",
            "close": "0.289267"
        },
        {
            "time": "26.12.2020 15:54",
            "open": "0.289267",
            "high": "0.289267",
            "low": "0.289267",
            "close": "0.289286"
        },
        {
            "time": "26.12.2020 15:55",
            "open": "0.289286",
            "high": "0.289286",
            "low": "0.289286",
            "close": "0.289507"
        },
        {
            "time": "26.12.2020 15:56",
            "open": "0.289507",
            "high": "0.289507",
            "low": "0.289507",
            "close": "0.289346"
        },
        {
            "time": "26.12.2020 15:57",
            "open": "0.289346",
            "high": "0.2895",
            "low": "0.289346",
            "close": "0.288819"
        },
        {
            "time": "26.12.2020 15:58",
            "open": "0.288819",
            "high": "0.288819",
            "low": "0.288819",
            "close": "0.288693"
        },
        {
            "time": "26.12.2020 16:01",
            "open": "0.288693",
            "high": "0.288693",
            "low": "0.288644",
            "close": "0.288688"
        },
        {
            "time": "26.12.2020 16:02",
            "open": "0.288688",
            "high": "0.288688",
            "low": "0.28849",
            "close": "0.289194"
        },
        {
            "time": "26.12.2020 16:04",
            "open": "0.289194",
            "high": "0.289194",
            "low": "0.289144",
            "close": "0.288918"
        },
        {
            "time": "26.12.2020 16:06",
            "open": "0.288918",
            "high": "0.288918",
            "low": "0.288918",
            "close": "0.288"
        },
        {
            "time": "26.12.2020 16:07",
            "open": "0.288",
            "high": "0.288779",
            "low": "0.287585",
            "close": "0.288779"
        },
        {
            "time": "26.12.2020 16:12",
            "open": "0.288779",
            "high": "0.288779",
            "low": "0.288779",
            "close": "0.288752"
        },
        {
            "time": "26.12.2020 16:14",
            "open": "0.288752",
            "high": "0.288752",
            "low": "0.288752",
            "close": "0.28762"
        },
        {
            "time": "26.12.2020 16:15",
            "open": "0.28762",
            "high": "0.28762",
            "low": "0.28762",
            "close": "0.287949"
        },
        {
            "time": "26.12.2020 16:16",
            "open": "0.287949",
            "high": "0.28806",
            "low": "0.287949",
            "close": "0.287912"
        },
        {
            "time": "26.12.2020 16:17",
            "open": "0.287912",
            "high": "0.288787",
            "low": "0.287912",
            "close": "0.28879"
        },
        {
            "time": "26.12.2020 16:19",
            "open": "0.28879",
            "high": "0.28879",
            "low": "0.28879",
            "close": "0.28879"
        },
        {
            "time": "26.12.2020 16:20",
            "open": "0.28879",
            "high": "0.28879",
            "low": "0.288038",
            "close": "0.288036"
        },
        {
            "time": "26.12.2020 16:21",
            "open": "0.288036",
            "high": "0.288036",
            "low": "0.288036",
            "close": "0.288036"
        },
        {
            "time": "26.12.2020 16:23",
            "open": "0.288036",
            "high": "0.288036",
            "low": "0.288036",
            "close": "0.288036"
        },
        {
            "time": "26.12.2020 16:25",
            "open": "0.288036",
            "high": "0.288036",
            "low": "0.288036",
            "close": "0.28713"
        },
        {
            "time": "26.12.2020 16:33",
            "open": "0.28713",
            "high": "0.28713",
            "low": "0.28713",
            "close": "0.288138"
        },
        {
            "time": "26.12.2020 16:35",
            "open": "0.288138",
            "high": "0.288138",
            "low": "0.288138",
            "close": "0.287291"
        },
        {
            "time": "26.12.2020 16:37",
            "open": "0.287291",
            "high": "0.287291",
            "low": "0.287291",
            "close": "0.287112"
        },
        {
            "time": "26.12.2020 16:40",
            "open": "0.287112",
            "high": "0.287112",
            "low": "0.286627",
            "close": "0.287685"
        },
        {
            "time": "26.12.2020 16:41",
            "open": "0.287685",
            "high": "0.287685",
            "low": "0.287685",
            "close": "0.287676"
        },
        {
            "time": "26.12.2020 16:43",
            "open": "0.287676",
            "high": "0.287676",
            "low": "0.287676",
            "close": "0.288598"
        },
        {
            "time": "26.12.2020 16:56",
            "open": "0.288598",
            "high": "0.288598",
            "low": "0.288598",
            "close": "0.288542"
        },
        {
            "time": "26.12.2020 16:58",
            "open": "0.288542",
            "high": "0.288542",
            "low": "0.288542",
            "close": "0.287575"
        },
        {
            "time": "26.12.2020 16:59",
            "open": "0.287575",
            "high": "0.287575",
            "low": "0.287575",
            "close": "0.289072"
        },
        {
            "time": "26.12.2020 17:03",
            "open": "0.289072",
            "high": "0.289072",
            "low": "0.287002",
            "close": "0.287074"
        },
        {
            "time": "26.12.2020 17:05",
            "open": "0.287074",
            "high": "0.288291",
            "low": "0.287074",
            "close": "0.288293"
        },
        {
            "time": "26.12.2020 17:07",
            "open": "0.288293",
            "high": "0.288293",
            "low": "0.288293",
            "close": "0.289491"
        },
        {
            "time": "26.12.2020 17:09",
            "open": "0.289491",
            "high": "0.289491",
            "low": "0.289491",
            "close": "0.288297"
        },
        {
            "time": "26.12.2020 17:10",
            "open": "0.288297",
            "high": "0.288297",
            "low": "0.288295",
            "close": "0.288295"
        },
        {
            "time": "26.12.2020 17:11",
            "open": "0.288295",
            "high": "0.288295",
            "low": "0.288089",
            "close": "0.288"
        },
        {
            "time": "26.12.2020 17:12",
            "open": "0.288",
            "high": "0.288",
            "low": "0.288",
            "close": "0.288"
        },
        {
            "time": "26.12.2020 17:13",
            "open": "0.288",
            "high": "0.288",
            "low": "0.287606",
            "close": "0.288"
        },
        {
            "time": "26.12.2020 17:14",
            "open": "0.288",
            "high": "0.288321",
            "low": "0.288",
            "close": "0.289222"
        },
        {
            "time": "26.12.2020 17:15",
            "open": "0.289222",
            "high": "0.289876",
            "low": "0.289222",
            "close": "0.290289"
        },
        {
            "time": "26.12.2020 17:17",
            "open": "0.290289",
            "high": "0.290289",
            "low": "0.290289",
            "close": "0.292"
        },
        {
            "time": "26.12.2020 17:18",
            "open": "0.292",
            "high": "0.292",
            "low": "0.292",
            "close": "0.2942"
        },
        {
            "time": "26.12.2020 17:21",
            "open": "0.2942",
            "high": "0.2942",
            "low": "0.292953",
            "close": "0.293326"
        },
        {
            "time": "26.12.2020 17:22",
            "open": "0.293326",
            "high": "0.2942",
            "low": "0.293326",
            "close": "0.29471"
        },
        {
            "time": "26.12.2020 17:23",
            "open": "0.29471",
            "high": "0.295",
            "low": "0.294415",
            "close": "0.29398"
        },
        {
            "time": "26.12.2020 17:25",
            "open": "0.29398",
            "high": "0.29398",
            "low": "0.29398",
            "close": "0.295"
        },
        {
            "time": "26.12.2020 17:27",
            "open": "0.295",
            "high": "0.295496",
            "low": "0.295",
            "close": "0.296"
        },
        {
            "time": "26.12.2020 17:28",
            "open": "0.296",
            "high": "0.296",
            "low": "0.296",
            "close": "0.295083"
        },
        {
            "time": "26.12.2020 17:31",
            "open": "0.295083",
            "high": "0.295083",
            "low": "0.295083",
            "close": "0.295658"
        },
        {
            "time": "26.12.2020 17:32",
            "open": "0.295658",
            "high": "0.295658",
            "low": "0.295658",
            "close": "0.296699"
        },
        {
            "time": "26.12.2020 17:34",
            "open": "0.296699",
            "high": "0.296699",
            "low": "0.296699",
            "close": "0.2968"
        },
        {
            "time": "26.12.2020 17:36",
            "open": "0.2968",
            "high": "0.297363",
            "low": "0.2968",
            "close": "0.298"
        },
        {
            "time": "26.12.2020 17:38",
            "open": "0.298",
            "high": "0.298",
            "low": "0.298",
            "close": "0.297458"
        },
        {
            "time": "26.12.2020 17:40",
            "open": "0.297458",
            "high": "0.297458",
            "low": "0.297458",
            "close": "0.297129"
        },
        {
            "time": "26.12.2020 17:41",
            "open": "0.297129",
            "high": "0.297129",
            "low": "0.297129",
            "close": "0.296197"
        },
        {
            "time": "26.12.2020 17:42",
            "open": "0.296197",
            "high": "0.296197",
            "low": "0.296197",
            "close": "0.2969"
        },
        {
            "time": "26.12.2020 17:43",
            "open": "0.2969",
            "high": "0.2969",
            "low": "0.2969",
            "close": "0.296291"
        },
        {
            "time": "26.12.2020 17:44",
            "open": "0.296291",
            "high": "0.296291",
            "low": "0.296291",
            "close": "0.295965"
        },
        {
            "time": "26.12.2020 17:45",
            "open": "0.295965",
            "high": "0.296867",
            "low": "0.295965",
            "close": "0.297129"
        },
        {
            "time": "26.12.2020 17:48",
            "open": "0.297129",
            "high": "0.299",
            "low": "0.297129",
            "close": "0.297626"
        },
        {
            "time": "26.12.2020 17:49",
            "open": "0.297626",
            "high": "0.297626",
            "low": "0.297626",
            "close": "0.299101"
        },
        {
            "time": "26.12.2020 17:51",
            "open": "0.299101",
            "high": "0.2993",
            "low": "0.299101",
            "close": "0.3"
        },
        {
            "time": "26.12.2020 17:52",
            "open": "0.3",
            "high": "0.3",
            "low": "0.3",
            "close": "0.299695"
        },
        {
            "time": "26.12.2020 17:57",
            "open": "0.299695",
            "high": "0.299695",
            "low": "0.299695",
            "close": "0.299246"
        },
        {
            "time": "26.12.2020 17:58",
            "open": "0.299246",
            "high": "0.299246",
            "low": "0.299246",
            "close": "0.299488"
        },
        {
            "time": "26.12.2020 17:59",
            "open": "0.299488",
            "high": "0.299488",
            "low": "0.299488",
            "close": "0.299794"
        },
        {
            "time": "26.12.2020 18:02",
            "open": "0.299794",
            "high": "0.299794",
            "low": "0.298835",
            "close": "0.297633"
        },
        {
            "time": "26.12.2020 18:06",
            "open": "0.297633",
            "high": "0.297633",
            "low": "0.297633",
            "close": "0.297572"
        },
        {
            "time": "26.12.2020 18:07",
            "open": "0.297572",
            "high": "0.297572",
            "low": "0.297572",
            "close": "0.298463"
        },
        {
            "time": "26.12.2020 18:08",
            "open": "0.298463",
            "high": "0.299608",
            "low": "0.298463",
            "close": "0.297768"
        },
        {
            "time": "26.12.2020 18:09",
            "open": "0.297768",
            "high": "0.297768",
            "low": "0.297768",
            "close": "0.298553"
        },
        {
            "time": "26.12.2020 18:10",
            "open": "0.298553",
            "high": "0.298553",
            "low": "0.297601",
            "close": "0.295101"
        },
        {
            "time": "26.12.2020 18:21",
            "open": "0.295101",
            "high": "0.295101",
            "low": "0.29508",
            "close": "0.294984"
        },
        {
            "time": "26.12.2020 18:25",
            "open": "0.294984",
            "high": "0.294984",
            "low": "0.294984",
            "close": "0.295273"
        },
        {
            "time": "26.12.2020 18:30",
            "open": "0.295273",
            "high": "0.295273",
            "low": "0.295273",
            "close": "0.295108"
        },
        {
            "time": "26.12.2020 18:38",
            "open": "0.295108",
            "high": "0.295108",
            "low": "0.295108",
            "close": "0.295481"
        },
        {
            "time": "26.12.2020 18:40",
            "open": "0.295481",
            "high": "0.295487",
            "low": "0.292811",
            "close": "0.295931"
        },
        {
            "time": "26.12.2020 18:45",
            "open": "0.295931",
            "high": "0.295931",
            "low": "0.295931",
            "close": "0.29668"
        },
        {
            "time": "26.12.2020 18:47",
            "open": "0.29668",
            "high": "0.296681",
            "low": "0.29668",
            "close": "0.295291"
        },
        {
            "time": "26.12.2020 18:49",
            "open": "0.295291",
            "high": "0.295291",
            "low": "0.295291",
            "close": "0.295767"
        },
        {
            "time": "26.12.2020 18:50",
            "open": "0.295767",
            "high": "0.295767",
            "low": "0.295767",
            "close": "0.296382"
        },
        {
            "time": "26.12.2020 18:51",
            "open": "0.296382",
            "high": "0.296382",
            "low": "0.296382",
            "close": "0.296567"
        },
        {
            "time": "26.12.2020 18:52",
            "open": "0.296567",
            "high": "0.296567",
            "low": "0.296567",
            "close": "0.295964"
        },
        {
            "time": "26.12.2020 18:54",
            "open": "0.295964",
            "high": "0.295964",
            "low": "0.295964",
            "close": "0.297489"
        },
        {
            "time": "26.12.2020 18:58",
            "open": "0.297489",
            "high": "0.297489",
            "low": "0.297489",
            "close": "0.296817"
        },
        {
            "time": "26.12.2020 19:00",
            "open": "0.296817",
            "high": "0.296817",
            "low": "0.296817",
            "close": "0.297972"
        },
        {
            "time": "26.12.2020 19:03",
            "open": "0.297972",
            "high": "0.297972",
            "low": "0.297972",
            "close": "0.3"
        },
        {
            "time": "26.12.2020 19:12",
            "open": "0.3",
            "high": "0.30015",
            "low": "0.3",
            "close": "0.299945"
        },
        {
            "time": "26.12.2020 19:14",
            "open": "0.299945",
            "high": "0.299945",
            "low": "0.299945",
            "close": "0.300497"
        },
        {
            "time": "26.12.2020 19:15",
            "open": "0.300497",
            "high": "0.300497",
            "low": "0.300497",
            "close": "0.299497"
        },
        {
            "time": "26.12.2020 19:16",
            "open": "0.299497",
            "high": "0.299497",
            "low": "0.299497",
            "close": "0.298308"
        },
        {
            "time": "26.12.2020 19:17",
            "open": "0.298308",
            "high": "0.298308",
            "low": "0.298308",
            "close": "0.298466"
        },
        {
            "time": "26.12.2020 19:21",
            "open": "0.298466",
            "high": "0.298466",
            "low": "0.298466",
            "close": "0.299322"
        },
        {
            "time": "26.12.2020 19:22",
            "open": "0.299322",
            "high": "0.299322",
            "low": "0.299322",
            "close": "0.297701"
        },
        {
            "time": "26.12.2020 19:27",
            "open": "0.297701",
            "high": "0.297701",
            "low": "0.297701",
            "close": "0.29926"
        },
        {
            "time": "26.12.2020 19:28",
            "open": "0.29926",
            "high": "0.29926",
            "low": "0.298723",
            "close": "0.29874"
        },
        {
            "time": "26.12.2020 19:29",
            "open": "0.29874",
            "high": "0.29874",
            "low": "0.298719",
            "close": "0.298578"
        },
        {
            "time": "26.12.2020 19:36",
            "open": "0.298578",
            "high": "0.298578",
            "low": "0.298578",
            "close": "0.298614"
        },
        {
            "time": "26.12.2020 19:41",
            "open": "0.298614",
            "high": "0.298614",
            "low": "0.298001",
            "close": "0.298693"
        },
        {
            "time": "26.12.2020 19:43",
            "open": "0.298693",
            "high": "0.298693",
            "low": "0.298693",
            "close": "0.298559"
        },
        {
            "time": "26.12.2020 19:44",
            "open": "0.298559",
            "high": "0.298559",
            "low": "0.298559",
            "close": "0.298559"
        },
        {
            "time": "26.12.2020 19:51",
            "open": "0.298559",
            "high": "0.298559",
            "low": "0.298385",
            "close": "0.298403"
        },
        {
            "time": "26.12.2020 19:52",
            "open": "0.298403",
            "high": "0.298403",
            "low": "0.29836",
            "close": "0.298001"
        },
        {
            "time": "26.12.2020 19:54",
            "open": "0.298001",
            "high": "0.298001",
            "low": "0.298001",
            "close": "0.298558"
        },
        {
            "time": "26.12.2020 19:56",
            "open": "0.298558",
            "high": "0.29858",
            "low": "0.298558",
            "close": "0.298056"
        },
        {
            "time": "26.12.2020 20:02",
            "open": "0.298056",
            "high": "0.298061",
            "low": "0.298056",
            "close": "0.298001"
        },
        {
            "time": "26.12.2020 20:03",
            "open": "0.298001",
            "high": "0.298001",
            "low": "0.297323",
            "close": "0.297256"
        },
        {
            "time": "26.12.2020 20:07",
            "open": "0.297256",
            "high": "0.297256",
            "low": "0.297256",
            "close": "0.297599"
        },
        {
            "time": "26.12.2020 20:15",
            "open": "0.297599",
            "high": "0.2976",
            "low": "0.297599",
            "close": "0.296675"
        },
        {
            "time": "26.12.2020 20:16",
            "open": "0.296675",
            "high": "0.296917",
            "low": "0.296253",
            "close": "0.296249"
        },
        {
            "time": "26.12.2020 20:17",
            "open": "0.296249",
            "high": "0.296249",
            "low": "0.296249",
            "close": "0.296259"
        },
        {
            "time": "26.12.2020 20:18",
            "open": "0.296259",
            "high": "0.296259",
            "low": "0.296259",
            "close": "0.296499"
        },
        {
            "time": "26.12.2020 20:19",
            "open": "0.296499",
            "high": "0.296499",
            "low": "0.296499",
            "close": "0.296499"
        },
        {
            "time": "26.12.2020 20:20",
            "open": "0.296499",
            "high": "0.296499",
            "low": "0.296499",
            "close": "0.296014"
        },
        {
            "time": "26.12.2020 20:26",
            "open": "0.296014",
            "high": "0.296014",
            "low": "0.296014",
            "close": "0.296328"
        },
        {
            "time": "26.12.2020 20:29",
            "open": "0.296328",
            "high": "0.296328",
            "low": "0.296328",
            "close": "0.296946"
        },
        {
            "time": "26.12.2020 20:32",
            "open": "0.296946",
            "high": "0.296946",
            "low": "0.296946",
            "close": "0.296629"
        },
        {
            "time": "26.12.2020 20:34",
            "open": "0.296629",
            "high": "0.296629",
            "low": "0.296629",
            "close": "0.296629"
        },
        {
            "time": "26.12.2020 20:35",
            "open": "0.296629",
            "high": "0.296629",
            "low": "0.296629",
            "close": "0.29624"
        },
        {
            "time": "26.12.2020 20:38",
            "open": "0.29624",
            "high": "0.29624",
            "low": "0.29624",
            "close": "0.296675"
        },
        {
            "time": "26.12.2020 20:39",
            "open": "0.296675",
            "high": "0.296675",
            "low": "0.296675",
            "close": "0.295998"
        },
        {
            "time": "26.12.2020 20:49",
            "open": "0.295998",
            "high": "0.295998",
            "low": "0.295998",
            "close": "0.296966"
        },
        {
            "time": "26.12.2020 20:50",
            "open": "0.296966",
            "high": "0.296966",
            "low": "0.296966",
            "close": "0.296524"
        },
        {
            "time": "26.12.2020 21:00",
            "open": "0.296524",
            "high": "0.296524",
            "low": "0.296524",
            "close": "0.294727"
        },
        {
            "time": "26.12.2020 21:03",
            "open": "0.294727",
            "high": "0.294727",
            "low": "0.294725",
            "close": "0.295755"
        },
        {
            "time": "26.12.2020 21:05",
            "open": "0.295755",
            "high": "0.295755",
            "low": "0.294957",
            "close": "0.294276"
        },
        {
            "time": "26.12.2020 21:06",
            "open": "0.294276",
            "high": "0.294276",
            "low": "0.294276",
            "close": "0.293997"
        },
        {
            "time": "26.12.2020 21:08",
            "open": "0.293997",
            "high": "0.293997",
            "low": "0.293997",
            "close": "0.291482"
        },
        {
            "time": "26.12.2020 21:11",
            "open": "0.291482",
            "high": "0.291482",
            "low": "0.291482",
            "close": "0.29134"
        },
        {
            "time": "26.12.2020 21:13",
            "open": "0.29134",
            "high": "0.29134",
            "low": "0.29134",
            "close": "0.291959"
        },
        {
            "time": "26.12.2020 21:17",
            "open": "0.291959",
            "high": "0.293136",
            "low": "0.291279",
            "close": "0.292299"
        },
        {
            "time": "26.12.2020 21:21",
            "open": "0.292299",
            "high": "0.292299",
            "low": "0.292299",
            "close": "0.293242"
        },
        {
            "time": "26.12.2020 21:23",
            "open": "0.293242",
            "high": "0.293242",
            "low": "0.292963",
            "close": "0.29285"
        },
        {
            "time": "26.12.2020 21:24",
            "open": "0.29285",
            "high": "0.29285",
            "low": "0.29285",
            "close": "0.294111"
        },
        {
            "time": "26.12.2020 21:26",
            "open": "0.294111",
            "high": "0.294111",
            "low": "0.294111",
            "close": "0.293995"
        },
        {
            "time": "26.12.2020 21:28",
            "open": "0.293995",
            "high": "0.293995",
            "low": "0.293995",
            "close": "0.293876"
        },
        {
            "time": "26.12.2020 21:35",
            "open": "0.293876",
            "high": "0.293876",
            "low": "0.293876",
            "close": "0.293777"
        },
        {
            "time": "26.12.2020 21:36",
            "open": "0.293777",
            "high": "0.293777",
            "low": "0.292929",
            "close": "0.291969"
        },
        {
            "time": "26.12.2020 21:38",
            "open": "0.291969",
            "high": "0.291969",
            "low": "0.291939",
            "close": "0.292146"
        },
        {
            "time": "26.12.2020 21:39",
            "open": "0.292146",
            "high": "0.29289",
            "low": "0.292146",
            "close": "0.291815"
        },
        {
            "time": "26.12.2020 21:40",
            "open": "0.291815",
            "high": "0.291815",
            "low": "0.291815",
            "close": "0.291816"
        },
        {
            "time": "26.12.2020 21:42",
            "open": "0.291816",
            "high": "0.291993",
            "low": "0.291814",
            "close": "0.292417"
        },
        {
            "time": "26.12.2020 21:44",
            "open": "0.292417",
            "high": "0.292417",
            "low": "0.292417",
            "close": "0.292138"
        },
        {
            "time": "26.12.2020 21:49",
            "open": "0.292138",
            "high": "0.292138",
            "low": "0.292138",
            "close": "0.292644"
        },
        {
            "time": "26.12.2020 21:53",
            "open": "0.292644",
            "high": "0.293539",
            "low": "0.292644",
            "close": "0.292522"
        },
        {
            "time": "26.12.2020 22:00",
            "open": "0.292522",
            "high": "0.292522",
            "low": "0.292522",
            "close": "0.29167"
        },
        {
            "time": "26.12.2020 22:04",
            "open": "0.29167",
            "high": "0.291848",
            "low": "0.29167",
            "close": "0.293028"
        },
        {
            "time": "26.12.2020 22:08",
            "open": "0.293028",
            "high": "0.29412",
            "low": "0.293028",
            "close": "0.293333"
        },
        {
            "time": "26.12.2020 22:11",
            "open": "0.293333",
            "high": "0.293333",
            "low": "0.293333",
            "close": "0.293332"
        },
        {
            "time": "26.12.2020 22:12",
            "open": "0.293332",
            "high": "0.293332",
            "low": "0.293332",
            "close": "0.293333"
        },
        {
            "time": "26.12.2020 22:14",
            "open": "0.293333",
            "high": "0.293333",
            "low": "0.293333",
            "close": "0.293116"
        },
        {
            "time": "26.12.2020 22:15",
            "open": "0.293116",
            "high": "0.293116",
            "low": "0.293114",
            "close": "0.293559"
        },
        {
            "time": "26.12.2020 22:19",
            "open": "0.293559",
            "high": "0.293559",
            "low": "0.293559",
            "close": "0.294135"
        },
        {
            "time": "26.12.2020 22:20",
            "open": "0.294135",
            "high": "0.294135",
            "low": "0.293952",
            "close": "0.29386"
        },
        {
            "time": "26.12.2020 22:21",
            "open": "0.29386",
            "high": "0.293861",
            "low": "0.29386",
            "close": "0.294338"
        },
        {
            "time": "26.12.2020 22:26",
            "open": "0.294338",
            "high": "0.294338",
            "low": "0.294338",
            "close": "0.293187"
        },
        {
            "time": "26.12.2020 22:31",
            "open": "0.293187",
            "high": "0.293187",
            "low": "0.293187",
            "close": "0.293051"
        },
        {
            "time": "26.12.2020 22:32",
            "open": "0.293051",
            "high": "0.293051",
            "low": "0.29305",
            "close": "0.293568"
        },
        {
            "time": "26.12.2020 22:33",
            "open": "0.293568",
            "high": "0.293568",
            "low": "0.293568",
            "close": "0.293113"
        },
        {
            "time": "26.12.2020 22:34",
            "open": "0.293113",
            "high": "0.293113",
            "low": "0.293113",
            "close": "0.293161"
        },
        {
            "time": "26.12.2020 22:36",
            "open": "0.293161",
            "high": "0.293161",
            "low": "0.293161",
            "close": "0.293018"
        },
        {
            "time": "26.12.2020 22:37",
            "open": "0.293018",
            "high": "0.293575",
            "low": "0.293018",
            "close": "0.293575"
        },
        {
            "time": "26.12.2020 22:38",
            "open": "0.293575",
            "high": "0.293575",
            "low": "0.293575",
            "close": "0.293575"
        },
        {
            "time": "26.12.2020 22:40",
            "open": "0.293575",
            "high": "0.293575",
            "low": "0.293161",
            "close": "0.293161"
        },
        {
            "time": "26.12.2020 22:41",
            "open": "0.293161",
            "high": "0.293161",
            "low": "0.293156",
            "close": "0.293942"
        },
        {
            "time": "26.12.2020 22:42",
            "open": "0.293942",
            "high": "0.293942",
            "low": "0.293942",
            "close": "0.293179"
        },
        {
            "time": "26.12.2020 22:47",
            "open": "0.293179",
            "high": "0.293179",
            "low": "0.293179",
            "close": "0.293157"
        },
        {
            "time": "26.12.2020 22:50",
            "open": "0.293157",
            "high": "0.293157",
            "low": "0.293157",
            "close": "0.2938"
        },
        {
            "time": "26.12.2020 22:51",
            "open": "0.2938",
            "high": "0.2938",
            "low": "0.2938",
            "close": "0.293018"
        },
        {
            "time": "26.12.2020 22:55",
            "open": "0.293018",
            "high": "0.29433",
            "low": "0.293018",
            "close": "0.293145"
        },
        {
            "time": "26.12.2020 22:58",
            "open": "0.293145",
            "high": "0.293145",
            "low": "0.293145",
            "close": "0.293072"
        },
        {
            "time": "26.12.2020 22:59",
            "open": "0.293072",
            "high": "0.293072",
            "low": "0.293072",
            "close": "0.293072"
        },
        {
            "time": "26.12.2020 23:04",
            "open": "0.293072",
            "high": "0.293072",
            "low": "0.293072",
            "close": "0.293"
        },
        {
            "time": "26.12.2020 23:10",
            "open": "0.293",
            "high": "0.293",
            "low": "0.293",
            "close": "0.293"
        },
        {
            "time": "26.12.2020 23:13",
            "open": "0.293",
            "high": "0.293",
            "low": "0.293",
            "close": "0.29312"
        },
        {
            "time": "26.12.2020 23:14",
            "open": "0.29312",
            "high": "0.29312",
            "low": "0.29312",
            "close": "0.291148"
        },
        {
            "time": "26.12.2020 23:15",
            "open": "0.291148",
            "high": "0.291148",
            "low": "0.29",
            "close": "0.29025"
        },
        {
            "time": "26.12.2020 23:18",
            "open": "0.29025",
            "high": "0.29025",
            "low": "0.29",
            "close": "0.292087"
        },
        {
            "time": "26.12.2020 23:19",
            "open": "0.292087",
            "high": "0.292087",
            "low": "0.292087",
            "close": "0.291094"
        },
        {
            "time": "26.12.2020 23:25",
            "open": "0.291094",
            "high": "0.291094",
            "low": "0.290328",
            "close": "0.290328"
        },
        {
            "time": "26.12.2020 23:27",
            "open": "0.290328",
            "high": "0.290328",
            "low": "0.290328",
            "close": "0.292126"
        },
        {
            "time": "26.12.2020 23:30",
            "open": "0.292126",
            "high": "0.292126",
            "low": "0.292126",
            "close": "0.290328"
        },
        {
            "time": "26.12.2020 23:31",
            "open": "0.290328",
            "high": "0.290328",
            "low": "0.289786",
            "close": "0.289786"
        },
        {
            "time": "26.12.2020 23:32",
            "open": "0.289786",
            "high": "0.289788",
            "low": "0.289786",
            "close": "0.289657"
        },
        {
            "time": "26.12.2020 23:33",
            "open": "0.289657",
            "high": "0.289657",
            "low": "0.288909",
            "close": "0.288872"
        },
        {
            "time": "26.12.2020 23:34",
            "open": "0.288872",
            "high": "0.288872",
            "low": "0.288872",
            "close": "0.290233"
        },
        {
            "time": "26.12.2020 23:38",
            "open": "0.290233",
            "high": "0.290233",
            "low": "0.290233",
            "close": "0.288872"
        },
        {
            "time": "26.12.2020 23:40",
            "open": "0.288872",
            "high": "0.288872",
            "low": "0.288872",
            "close": "0.28911"
        },
        {
            "time": "26.12.2020 23:42",
            "open": "0.28911",
            "high": "0.289111",
            "low": "0.28911",
            "close": "0.289385"
        },
        {
            "time": "26.12.2020 23:43",
            "open": "0.289385",
            "high": "0.289385",
            "low": "0.289385",
            "close": "0.288656"
        },
        {
            "time": "26.12.2020 23:44",
            "open": "0.288656",
            "high": "0.289739",
            "low": "0.288656",
            "close": "0.288684"
        },
        {
            "time": "26.12.2020 23:45",
            "open": "0.288684",
            "high": "0.288684",
            "low": "0.288684",
            "close": "0.28966"
        },
        {
            "time": "26.12.2020 23:48",
            "open": "0.28966",
            "high": "0.289666",
            "low": "0.28966",
            "close": "0.28888"
        },
        {
            "time": "26.12.2020 23:52",
            "open": "0.28888",
            "high": "0.28888",
            "low": "0.28888",
            "close": "0.290063"
        },
        {
            "time": "26.12.2020 23:55",
            "open": "0.290063",
            "high": "0.290063",
            "low": "0.290063",
            "close": "0.289449"
        }
    ]
}