{
    "ZRX-EUR": [
        {
            "time": "12.01.2021 15:05",
            "open": "0.345471",
            "high": "0.345471",
            "low": "0.345471",
            "close": "0.341924"
        },
        {
            "time": "12.01.2021 15:06",
            "open": "0.341924",
            "high": "0.343918",
            "low": "0.341924",
            "close": "0.343643"
        },
        {
            "time": "12.01.2021 15:07",
            "open": "0.343643",
            "high": "0.343643",
            "low": "0.343643",
            "close": "0.343833"
        },
        {
            "time": "12.01.2021 15:10",
            "open": "0.343833",
            "high": "0.343833",
            "low": "0.343833",
            "close": "0.343833"
        },
        {
            "time": "12.01.2021 15:11",
            "open": "0.343833",
            "high": "0.343833",
            "low": "0.343833",
            "close": "0.34283"
        },
        {
            "time": "12.01.2021 15:12",
            "open": "0.34283",
            "high": "0.34619",
            "low": "0.34283",
            "close": "0.346647"
        },
        {
            "time": "12.01.2021 15:13",
            "open": "0.346647",
            "high": "0.346647",
            "low": "0.346647",
            "close": "0.345121"
        },
        {
            "time": "12.01.2021 15:15",
            "open": "0.345121",
            "high": "0.346278",
            "low": "0.34512",
            "close": "0.34512"
        },
        {
            "time": "12.01.2021 15:16",
            "open": "0.34512",
            "high": "0.34839",
            "low": "0.34512",
            "close": "0.348241"
        },
        {
            "time": "12.01.2021 15:17",
            "open": "0.348241",
            "high": "0.348241",
            "low": "0.347",
            "close": "0.345616"
        },
        {
            "time": "12.01.2021 15:19",
            "open": "0.345616",
            "high": "0.345616",
            "low": "0.345616",
            "close": "0.346295"
        },
        {
            "time": "12.01.2021 15:22",
            "open": "0.346295",
            "high": "0.346295",
            "low": "0.346295",
            "close": "0.343214"
        },
        {
            "time": "12.01.2021 15:23",
            "open": "0.343214",
            "high": "0.343214",
            "low": "0.343214",
            "close": "0.342806"
        },
        {
            "time": "12.01.2021 15:25",
            "open": "0.342806",
            "high": "0.346506",
            "low": "0.341534",
            "close": "0.342902"
        },
        {
            "time": "12.01.2021 15:26",
            "open": "0.342902",
            "high": "0.342902",
            "low": "0.342902",
            "close": "0.34"
        },
        {
            "time": "12.01.2021 15:27",
            "open": "0.34",
            "high": "0.34",
            "low": "0.339",
            "close": "0.339465"
        },
        {
            "time": "12.01.2021 15:29",
            "open": "0.339465",
            "high": "0.34089",
            "low": "0.339465",
            "close": "0.341"
        },
        {
            "time": "12.01.2021 15:30",
            "open": "0.341",
            "high": "0.341",
            "low": "0.341",
            "close": "0.341102"
        },
        {
            "time": "12.01.2021 15:31",
            "open": "0.341102",
            "high": "0.34114",
            "low": "0.341102",
            "close": "0.341184"
        },
        {
            "time": "12.01.2021 15:34",
            "open": "0.341184",
            "high": "0.341184",
            "low": "0.341184",
            "close": "0.338758"
        },
        {
            "time": "12.01.2021 15:35",
            "open": "0.338758",
            "high": "0.338758",
            "low": "0.337006",
            "close": "0.337886"
        },
        {
            "time": "12.01.2021 15:36",
            "open": "0.337886",
            "high": "0.337886",
            "low": "0.337886",
            "close": "0.337886"
        },
        {
            "time": "12.01.2021 15:37",
            "open": "0.337886",
            "high": "0.337886",
            "low": "0.337227",
            "close": "0.337009"
        },
        {
            "time": "12.01.2021 15:39",
            "open": "0.337009",
            "high": "0.337009",
            "low": "0.337009",
            "close": "0.341926"
        },
        {
            "time": "12.01.2021 15:40",
            "open": "0.341926",
            "high": "0.341927",
            "low": "0.339518",
            "close": "0.340484"
        },
        {
            "time": "12.01.2021 15:41",
            "open": "0.340484",
            "high": "0.340484",
            "low": "0.340484",
            "close": "0.341725"
        },
        {
            "time": "12.01.2021 15:42",
            "open": "0.341725",
            "high": "0.341725",
            "low": "0.341301",
            "close": "0.343366"
        },
        {
            "time": "12.01.2021 15:43",
            "open": "0.343366",
            "high": "0.343415",
            "low": "0.3401",
            "close": "0.342447"
        },
        {
            "time": "12.01.2021 15:44",
            "open": "0.342447",
            "high": "0.342447",
            "low": "0.340447",
            "close": "0.343269"
        },
        {
            "time": "12.01.2021 15:47",
            "open": "0.343269",
            "high": "0.343269",
            "low": "0.343269",
            "close": "0.342828"
        },
        {
            "time": "12.01.2021 15:49",
            "open": "0.342828",
            "high": "0.342828",
            "low": "0.342826",
            "close": "0.341568"
        },
        {
            "time": "12.01.2021 15:50",
            "open": "0.341568",
            "high": "0.341568",
            "low": "0.341568",
            "close": "0.340992"
        },
        {
            "time": "12.01.2021 15:51",
            "open": "0.340992",
            "high": "0.341446",
            "low": "0.340991",
            "close": "0.343172"
        },
        {
            "time": "12.01.2021 15:52",
            "open": "0.343172",
            "high": "0.343172",
            "low": "0.341444",
            "close": "0.344774"
        },
        {
            "time": "12.01.2021 15:53",
            "open": "0.344774",
            "high": "0.344774",
            "low": "0.343499",
            "close": "0.34353"
        },
        {
            "time": "12.01.2021 15:54",
            "open": "0.34353",
            "high": "0.34353",
            "low": "0.34353",
            "close": "0.34367"
        },
        {
            "time": "12.01.2021 15:55",
            "open": "0.34367",
            "high": "0.34367",
            "low": "0.34367",
            "close": "0.345427"
        },
        {
            "time": "12.01.2021 15:59",
            "open": "0.345427",
            "high": "0.345427",
            "low": "0.343985",
            "close": "0.346702"
        },
        {
            "time": "12.01.2021 16:00",
            "open": "0.346702",
            "high": "0.346842",
            "low": "0.346702",
            "close": "0.347106"
        },
        {
            "time": "12.01.2021 16:01",
            "open": "0.347106",
            "high": "0.347106",
            "low": "0.347106",
            "close": "0.347278"
        },
        {
            "time": "12.01.2021 16:04",
            "open": "0.347278",
            "high": "0.347278",
            "low": "0.347278",
            "close": "0.347177"
        },
        {
            "time": "12.01.2021 16:05",
            "open": "0.347177",
            "high": "0.347177",
            "low": "0.346191",
            "close": "0.346678"
        },
        {
            "time": "12.01.2021 16:09",
            "open": "0.346678",
            "high": "0.346678",
            "low": "0.346678",
            "close": "0.344323"
        },
        {
            "time": "12.01.2021 16:10",
            "open": "0.344323",
            "high": "0.347373",
            "low": "0.344323",
            "close": "0.347632"
        },
        {
            "time": "12.01.2021 16:12",
            "open": "0.347632",
            "high": "0.348",
            "low": "0.347632",
            "close": "0.348"
        },
        {
            "time": "12.01.2021 16:14",
            "open": "0.348",
            "high": "0.348",
            "low": "0.347537",
            "close": "0.347537"
        },
        {
            "time": "12.01.2021 16:15",
            "open": "0.347537",
            "high": "0.347537",
            "low": "0.346431",
            "close": "0.348844"
        },
        {
            "time": "12.01.2021 16:16",
            "open": "0.348844",
            "high": "0.348844",
            "low": "0.348844",
            "close": "0.348698"
        },
        {
            "time": "12.01.2021 16:19",
            "open": "0.348698",
            "high": "0.348698",
            "low": "0.348698",
            "close": "0.348699"
        },
        {
            "time": "12.01.2021 16:20",
            "open": "0.348699",
            "high": "0.34899",
            "low": "0.347836",
            "close": "0.348989"
        },
        {
            "time": "12.01.2021 16:21",
            "open": "0.348989",
            "high": "0.348989",
            "low": "0.348989",
            "close": "0.34899"
        },
        {
            "time": "12.01.2021 16:22",
            "open": "0.34899",
            "high": "0.349676",
            "low": "0.34899",
            "close": "0.349676"
        },
        {
            "time": "12.01.2021 16:23",
            "open": "0.349676",
            "high": "0.35",
            "low": "0.349676",
            "close": "0.349788"
        },
        {
            "time": "12.01.2021 16:24",
            "open": "0.349788",
            "high": "0.351237",
            "low": "0.349788",
            "close": "0.351236"
        },
        {
            "time": "12.01.2021 16:26",
            "open": "0.351236",
            "high": "0.35214",
            "low": "0.351155",
            "close": "0.353"
        },
        {
            "time": "12.01.2021 16:27",
            "open": "0.353",
            "high": "0.35382",
            "low": "0.353",
            "close": "0.35382"
        },
        {
            "time": "12.01.2021 16:28",
            "open": "0.35382",
            "high": "0.354",
            "low": "0.35382",
            "close": "0.354"
        },
        {
            "time": "12.01.2021 16:29",
            "open": "0.354",
            "high": "0.354859",
            "low": "0.354",
            "close": "0.354084"
        },
        {
            "time": "12.01.2021 16:30",
            "open": "0.354084",
            "high": "0.354084",
            "low": "0.352653",
            "close": "0.35139"
        },
        {
            "time": "12.01.2021 16:31",
            "open": "0.35139",
            "high": "0.351672",
            "low": "0.35139",
            "close": "0.352024"
        },
        {
            "time": "12.01.2021 16:33",
            "open": "0.352024",
            "high": "0.352024",
            "low": "0.351672",
            "close": "0.353649"
        },
        {
            "time": "12.01.2021 16:34",
            "open": "0.353649",
            "high": "0.353649",
            "low": "0.353649",
            "close": "0.352071"
        },
        {
            "time": "12.01.2021 16:35",
            "open": "0.352071",
            "high": "0.352071",
            "low": "0.352069",
            "close": "0.354281"
        },
        {
            "time": "12.01.2021 16:38",
            "open": "0.354281",
            "high": "0.354281",
            "low": "0.354281",
            "close": "0.35394"
        },
        {
            "time": "12.01.2021 16:44",
            "open": "0.35394",
            "high": "0.354365",
            "low": "0.35394",
            "close": "0.354"
        },
        {
            "time": "12.01.2021 16:46",
            "open": "0.354",
            "high": "0.354",
            "low": "0.353069",
            "close": "0.353069"
        },
        {
            "time": "12.01.2021 16:47",
            "open": "0.353069",
            "high": "0.353069",
            "low": "0.351678",
            "close": "0.354013"
        },
        {
            "time": "12.01.2021 16:48",
            "open": "0.354013",
            "high": "0.354013",
            "low": "0.354013",
            "close": "0.354981"
        },
        {
            "time": "12.01.2021 16:50",
            "open": "0.354981",
            "high": "0.355",
            "low": "0.354981",
            "close": "0.355293"
        },
        {
            "time": "12.01.2021 16:52",
            "open": "0.355293",
            "high": "0.355293",
            "low": "0.353376",
            "close": "0.353376"
        },
        {
            "time": "12.01.2021 16:53",
            "open": "0.353376",
            "high": "0.353376",
            "low": "0.353376",
            "close": "0.353371"
        },
        {
            "time": "12.01.2021 16:55",
            "open": "0.353371",
            "high": "0.353371",
            "low": "0.352673",
            "close": "0.354"
        },
        {
            "time": "12.01.2021 16:57",
            "open": "0.354",
            "high": "0.354245",
            "low": "0.352614",
            "close": "0.353271"
        },
        {
            "time": "12.01.2021 16:58",
            "open": "0.353271",
            "high": "0.353271",
            "low": "0.353271",
            "close": "0.351215"
        },
        {
            "time": "12.01.2021 16:59",
            "open": "0.351215",
            "high": "0.351215",
            "low": "0.350826",
            "close": "0.356"
        },
        {
            "time": "12.01.2021 17:02",
            "open": "0.356",
            "high": "0.356",
            "low": "0.356",
            "close": "0.35612"
        },
        {
            "time": "12.01.2021 17:03",
            "open": "0.35612",
            "high": "0.356588",
            "low": "0.35612",
            "close": "0.354887"
        },
        {
            "time": "12.01.2021 17:04",
            "open": "0.354887",
            "high": "0.357025",
            "low": "0.354887",
            "close": "0.357981"
        },
        {
            "time": "12.01.2021 17:06",
            "open": "0.357981",
            "high": "0.358",
            "low": "0.35798",
            "close": "0.356937"
        },
        {
            "time": "12.01.2021 17:08",
            "open": "0.356937",
            "high": "0.358134",
            "low": "0.356817",
            "close": "0.358134"
        },
        {
            "time": "12.01.2021 17:09",
            "open": "0.358134",
            "high": "0.359609",
            "low": "0.358134",
            "close": "0.359523"
        },
        {
            "time": "12.01.2021 17:10",
            "open": "0.359523",
            "high": "0.359523",
            "low": "0.359039",
            "close": "0.357789"
        },
        {
            "time": "12.01.2021 17:12",
            "open": "0.357789",
            "high": "0.359065",
            "low": "0.357787",
            "close": "0.359635"
        },
        {
            "time": "12.01.2021 17:14",
            "open": "0.359635",
            "high": "0.359635",
            "low": "0.356988",
            "close": "0.358509"
        },
        {
            "time": "12.01.2021 17:15",
            "open": "0.358509",
            "high": "0.358509",
            "low": "0.358103",
            "close": "0.357369"
        },
        {
            "time": "12.01.2021 17:17",
            "open": "0.357369",
            "high": "0.357369",
            "low": "0.357369",
            "close": "0.359129"
        },
        {
            "time": "12.01.2021 17:18",
            "open": "0.359129",
            "high": "0.359129",
            "low": "0.359129",
            "close": "0.359848"
        },
        {
            "time": "12.01.2021 17:20",
            "open": "0.359848",
            "high": "0.359848",
            "low": "0.359848",
            "close": "0.359129"
        },
        {
            "time": "12.01.2021 17:21",
            "open": "0.359129",
            "high": "0.359129",
            "low": "0.359129",
            "close": "0.359903"
        },
        {
            "time": "12.01.2021 17:22",
            "open": "0.359903",
            "high": "0.3603",
            "low": "0.359903",
            "close": "0.360782"
        },
        {
            "time": "12.01.2021 17:24",
            "open": "0.360782",
            "high": "0.360858",
            "low": "0.3603",
            "close": "0.360823"
        },
        {
            "time": "12.01.2021 17:25",
            "open": "0.360823",
            "high": "0.361356",
            "low": "0.359554",
            "close": "0.360912"
        },
        {
            "time": "12.01.2021 17:26",
            "open": "0.360912",
            "high": "0.360912",
            "low": "0.360912",
            "close": "0.360881"
        },
        {
            "time": "12.01.2021 17:27",
            "open": "0.360881",
            "high": "0.361768",
            "low": "0.360881",
            "close": "0.36178"
        },
        {
            "time": "12.01.2021 17:30",
            "open": "0.36178",
            "high": "0.361998",
            "low": "0.36178",
            "close": "0.357704"
        },
        {
            "time": "12.01.2021 17:32",
            "open": "0.357704",
            "high": "0.357704",
            "low": "0.357704",
            "close": "0.360828"
        },
        {
            "time": "12.01.2021 17:34",
            "open": "0.360828",
            "high": "0.360828",
            "low": "0.359386",
            "close": "0.359359"
        },
        {
            "time": "12.01.2021 17:36",
            "open": "0.359359",
            "high": "0.359373",
            "low": "0.359359",
            "close": "0.360628"
        },
        {
            "time": "12.01.2021 17:39",
            "open": "0.360628",
            "high": "0.360628",
            "low": "0.360628",
            "close": "0.359979"
        },
        {
            "time": "12.01.2021 17:40",
            "open": "0.359979",
            "high": "0.359979",
            "low": "0.359979",
            "close": "0.35999"
        },
        {
            "time": "12.01.2021 17:41",
            "open": "0.360338",
            "high": "0.360338",
            "low": "0.360338",
            "close": "0.360065"
        },
        {
            "time": "12.01.2021 17:46",
            "open": "0.360065",
            "high": "0.360066",
            "low": "0.360065",
            "close": "0.360213"
        },
        {
            "time": "12.01.2021 17:47",
            "open": "0.360213",
            "high": "0.361292",
            "low": "0.360117",
            "close": "0.360066"
        },
        {
            "time": "12.01.2021 17:48",
            "open": "0.360066",
            "high": "0.360066",
            "low": "0.360066",
            "close": "0.360065"
        },
        {
            "time": "12.01.2021 17:50",
            "open": "0.360065",
            "high": "0.360065",
            "low": "0.358769",
            "close": "0.358469"
        },
        {
            "time": "12.01.2021 17:51",
            "open": "0.358469",
            "high": "0.358469",
            "low": "0.358469",
            "close": "0.360066"
        },
        {
            "time": "12.01.2021 17:52",
            "open": "0.360066",
            "high": "0.360066",
            "low": "0.360066",
            "close": "0.359944"
        },
        {
            "time": "12.01.2021 17:53",
            "open": "0.359944",
            "high": "0.361292",
            "low": "0.359944",
            "close": "0.362"
        },
        {
            "time": "12.01.2021 17:54",
            "open": "0.362",
            "high": "0.362648",
            "low": "0.362",
            "close": "0.362678"
        },
        {
            "time": "12.01.2021 17:55",
            "open": "0.362678",
            "high": "0.362678",
            "low": "0.362678",
            "close": "0.362678"
        },
        {
            "time": "12.01.2021 17:56",
            "open": "0.362678",
            "high": "0.363455",
            "low": "0.362678",
            "close": "0.363396"
        },
        {
            "time": "12.01.2021 17:58",
            "open": "0.363396",
            "high": "0.363396",
            "low": "0.363318",
            "close": "0.363455"
        },
        {
            "time": "12.01.2021 17:59",
            "open": "0.363455",
            "high": "0.363576",
            "low": "0.363455",
            "close": "0.363576"
        },
        {
            "time": "12.01.2021 18:00",
            "open": "0.363576",
            "high": "0.365071",
            "low": "0.363576",
            "close": "0.36341"
        },
        {
            "time": "12.01.2021 18:01",
            "open": "0.36341",
            "high": "0.36341",
            "low": "0.36341",
            "close": "0.363784"
        },
        {
            "time": "12.01.2021 18:02",
            "open": "0.363784",
            "high": "0.363784",
            "low": "0.363784",
            "close": "0.362171"
        },
        {
            "time": "12.01.2021 18:03",
            "open": "0.362171",
            "high": "0.36358",
            "low": "0.362099",
            "close": "0.362436"
        },
        {
            "time": "12.01.2021 18:04",
            "open": "0.362436",
            "high": "0.362436",
            "low": "0.362436",
            "close": "0.3626"
        },
        {
            "time": "12.01.2021 18:05",
            "open": "0.3626",
            "high": "0.362601",
            "low": "0.3626",
            "close": "0.363082"
        },
        {
            "time": "12.01.2021 18:08",
            "open": "0.363082",
            "high": "0.363082",
            "low": "0.363082",
            "close": "0.36521"
        },
        {
            "time": "12.01.2021 18:11",
            "open": "0.36521",
            "high": "0.365282",
            "low": "0.365168",
            "close": "0.363556"
        },
        {
            "time": "12.01.2021 18:12",
            "open": "0.363556",
            "high": "0.363556",
            "low": "0.36343",
            "close": "0.363898"
        },
        {
            "time": "12.01.2021 18:13",
            "open": "0.363898",
            "high": "0.364336",
            "low": "0.363878",
            "close": "0.362543"
        },
        {
            "time": "12.01.2021 18:14",
            "open": "0.362543",
            "high": "0.362546",
            "low": "0.362345",
            "close": "0.363171"
        },
        {
            "time": "12.01.2021 18:16",
            "open": "0.363171",
            "high": "0.363171",
            "low": "0.362",
            "close": "0.362341"
        },
        {
            "time": "12.01.2021 18:20",
            "open": "0.362341",
            "high": "0.362924",
            "low": "0.361769",
            "close": "0.360979"
        },
        {
            "time": "12.01.2021 18:21",
            "open": "0.360979",
            "high": "0.360979",
            "low": "0.360979",
            "close": "0.360876"
        },
        {
            "time": "12.01.2021 18:22",
            "open": "0.360876",
            "high": "0.362717",
            "low": "0.360753",
            "close": "0.361017"
        },
        {
            "time": "12.01.2021 18:23",
            "open": "0.361017",
            "high": "0.36245",
            "low": "0.361017",
            "close": "0.361975"
        },
        {
            "time": "12.01.2021 18:24",
            "open": "0.361975",
            "high": "0.361975",
            "low": "0.361975",
            "close": "0.361022"
        },
        {
            "time": "12.01.2021 18:25",
            "open": "0.361022",
            "high": "0.361022",
            "low": "0.361021",
            "close": "0.36139"
        },
        {
            "time": "12.01.2021 18:27",
            "open": "0.36139",
            "high": "0.36139",
            "low": "0.36139",
            "close": "0.361792"
        },
        {
            "time": "12.01.2021 18:29",
            "open": "0.361792",
            "high": "0.361792",
            "low": "0.361792",
            "close": "0.358987"
        },
        {
            "time": "12.01.2021 18:30",
            "open": "0.358987",
            "high": "0.358987",
            "low": "0.358987",
            "close": "0.362"
        },
        {
            "time": "12.01.2021 18:31",
            "open": "0.362",
            "high": "0.362008",
            "low": "0.362",
            "close": "0.361698"
        },
        {
            "time": "12.01.2021 18:32",
            "open": "0.361698",
            "high": "0.361698",
            "low": "0.361698",
            "close": "0.361781"
        },
        {
            "time": "12.01.2021 18:34",
            "open": "0.361781",
            "high": "0.361781",
            "low": "0.361781",
            "close": "0.360619"
        },
        {
            "time": "12.01.2021 18:36",
            "open": "0.360619",
            "high": "0.360619",
            "low": "0.360619",
            "close": "0.359055"
        },
        {
            "time": "12.01.2021 18:37",
            "open": "0.359055",
            "high": "0.359055",
            "low": "0.359055",
            "close": "0.360506"
        },
        {
            "time": "12.01.2021 18:38",
            "open": "0.360506",
            "high": "0.360524",
            "low": "0.360506",
            "close": "0.360932"
        }
    ]
}