{
    "EOS-EUR": [
        {
            "time": "13.12.2020 23:58",
            "open": "2.341",
            "high": "2.341",
            "low": "2.341",
            "close": "2.342"
        },
        {
            "time": "14.12.2020 00:00",
            "open": "2.342",
            "high": "2.342",
            "low": "2.342",
            "close": "2.344"
        },
        {
            "time": "14.12.2020 00:03",
            "open": "2.344",
            "high": "2.344",
            "low": "2.344",
            "close": "2.351"
        },
        {
            "time": "14.12.2020 00:11",
            "open": "2.351",
            "high": "2.351",
            "low": "2.351",
            "close": "2.346"
        },
        {
            "time": "14.12.2020 00:15",
            "open": "2.346",
            "high": "2.346",
            "low": "2.346",
            "close": "2.35"
        },
        {
            "time": "14.12.2020 00:17",
            "open": "2.35",
            "high": "2.35",
            "low": "2.35",
            "close": "2.348"
        },
        {
            "time": "14.12.2020 00:19",
            "open": "2.348",
            "high": "2.348",
            "low": "2.348",
            "close": "2.349"
        },
        {
            "time": "14.12.2020 00:22",
            "open": "2.349",
            "high": "2.349",
            "low": "2.349",
            "close": "2.348"
        },
        {
            "time": "14.12.2020 00:24",
            "open": "2.348",
            "high": "2.348",
            "low": "2.348",
            "close": "2.349"
        },
        {
            "time": "14.12.2020 00:25",
            "open": "2.349",
            "high": "2.349",
            "low": "2.349",
            "close": "2.345"
        },
        {
            "time": "14.12.2020 00:36",
            "open": "2.345",
            "high": "2.346",
            "low": "2.345",
            "close": "2.345"
        },
        {
            "time": "14.12.2020 00:38",
            "open": "2.345",
            "high": "2.345",
            "low": "2.345",
            "close": "2.342"
        },
        {
            "time": "14.12.2020 00:40",
            "open": "2.342",
            "high": "2.342",
            "low": "2.342",
            "close": "2.343"
        },
        {
            "time": "14.12.2020 00:42",
            "open": "2.343",
            "high": "2.343",
            "low": "2.343",
            "close": "2.34"
        },
        {
            "time": "14.12.2020 00:43",
            "open": "2.34",
            "high": "2.34",
            "low": "2.34",
            "close": "2.348"
        },
        {
            "time": "14.12.2020 00:53",
            "open": "2.348",
            "high": "2.348",
            "low": "2.348",
            "close": "2.345"
        },
        {
            "time": "14.12.2020 00:55",
            "open": "2.345",
            "high": "2.345",
            "low": "2.345",
            "close": "2.348"
        },
        {
            "time": "14.12.2020 00:59",
            "open": "2.348",
            "high": "2.348",
            "low": "2.348",
            "close": "2.339"
        },
        {
            "time": "14.12.2020 01:01",
            "open": "2.339",
            "high": "2.339",
            "low": "2.339",
            "close": "2.345"
        },
        {
            "time": "14.12.2020 01:03",
            "open": "2.345",
            "high": "2.345",
            "low": "2.345",
            "close": "2.337"
        },
        {
            "time": "14.12.2020 01:07",
            "open": "2.337",
            "high": "2.337",
            "low": "2.337",
            "close": "2.333"
        },
        {
            "time": "14.12.2020 01:10",
            "open": "2.333",
            "high": "2.333",
            "low": "2.333",
            "close": "2.332"
        },
        {
            "time": "14.12.2020 01:11",
            "open": "2.332",
            "high": "2.332",
            "low": "2.331",
            "close": "2.328"
        },
        {
            "time": "14.12.2020 01:12",
            "open": "2.328",
            "high": "2.328",
            "low": "2.325",
            "close": "2.332"
        },
        {
            "time": "14.12.2020 01:13",
            "open": "2.332",
            "high": "2.332",
            "low": "2.332",
            "close": "2.331"
        },
        {
            "time": "14.12.2020 01:14",
            "open": "2.331",
            "high": "2.331",
            "low": "2.331",
            "close": "2.332"
        },
        {
            "time": "14.12.2020 01:15",
            "open": "2.332",
            "high": "2.332",
            "low": "2.332",
            "close": "2.331"
        },
        {
            "time": "14.12.2020 01:36",
            "open": "2.331",
            "high": "2.331",
            "low": "2.331",
            "close": "2.329"
        },
        {
            "time": "14.12.2020 01:37",
            "open": "2.329",
            "high": "2.329",
            "low": "2.329",
            "close": "2.327"
        },
        {
            "time": "14.12.2020 01:38",
            "open": "2.327",
            "high": "2.327",
            "low": "2.327",
            "close": "2.321"
        },
        {
            "time": "14.12.2020 01:46",
            "open": "2.321",
            "high": "2.321",
            "low": "2.318",
            "close": "2.319"
        },
        {
            "time": "14.12.2020 01:49",
            "open": "2.319",
            "high": "2.32",
            "low": "2.319",
            "close": "2.318"
        },
        {
            "time": "14.12.2020 01:50",
            "open": "2.318",
            "high": "2.318",
            "low": "2.318",
            "close": "2.323"
        },
        {
            "time": "14.12.2020 02:02",
            "open": "2.323",
            "high": "2.323",
            "low": "2.323",
            "close": "2.324"
        },
        {
            "time": "14.12.2020 02:04",
            "open": "2.324",
            "high": "2.324",
            "low": "2.323",
            "close": "2.329"
        },
        {
            "time": "14.12.2020 02:05",
            "open": "2.329",
            "high": "2.329",
            "low": "2.329",
            "close": "2.324"
        },
        {
            "time": "14.12.2020 02:11",
            "open": "2.324",
            "high": "2.326",
            "low": "2.324",
            "close": "2.335"
        },
        {
            "time": "14.12.2020 02:27",
            "open": "2.335",
            "high": "2.335",
            "low": "2.335",
            "close": "2.334"
        },
        {
            "time": "14.12.2020 02:28",
            "open": "2.334",
            "high": "2.334",
            "low": "2.334",
            "close": "2.332"
        },
        {
            "time": "14.12.2020 02:29",
            "open": "2.332",
            "high": "2.332",
            "low": "2.332",
            "close": "2.33"
        },
        {
            "time": "14.12.2020 02:50",
            "open": "2.33",
            "high": "2.33",
            "low": "2.329",
            "close": "2.326"
        },
        {
            "time": "14.12.2020 02:52",
            "open": "2.326",
            "high": "2.327",
            "low": "2.326",
            "close": "2.327"
        },
        {
            "time": "14.12.2020 03:10",
            "open": "2.327",
            "high": "2.327",
            "low": "2.327",
            "close": "2.334"
        },
        {
            "time": "14.12.2020 03:17",
            "open": "2.334",
            "high": "2.334",
            "low": "2.334",
            "close": "2.333"
        },
        {
            "time": "14.12.2020 03:23",
            "open": "2.333",
            "high": "2.333",
            "low": "2.333",
            "close": "2.33"
        },
        {
            "time": "14.12.2020 03:24",
            "open": "2.33",
            "high": "2.33",
            "low": "2.33",
            "close": "2.333"
        },
        {
            "time": "14.12.2020 03:25",
            "open": "2.333",
            "high": "2.333",
            "low": "2.333",
            "close": "2.332"
        },
        {
            "time": "14.12.2020 03:26",
            "open": "2.332",
            "high": "2.333",
            "low": "2.332",
            "close": "2.336"
        },
        {
            "time": "14.12.2020 03:29",
            "open": "2.336",
            "high": "2.336",
            "low": "2.333",
            "close": "2.334"
        },
        {
            "time": "14.12.2020 03:37",
            "open": "2.334",
            "high": "2.334",
            "low": "2.334",
            "close": "2.343"
        },
        {
            "time": "14.12.2020 03:45",
            "open": "2.343",
            "high": "2.343",
            "low": "2.343",
            "close": "2.342"
        },
        {
            "time": "14.12.2020 03:46",
            "open": "2.342",
            "high": "2.342",
            "low": "2.342",
            "close": "2.342"
        },
        {
            "time": "14.12.2020 03:47",
            "open": "2.342",
            "high": "2.342",
            "low": "2.342",
            "close": "2.341"
        },
        {
            "time": "14.12.2020 03:48",
            "open": "2.341",
            "high": "2.341",
            "low": "2.341",
            "close": "2.342"
        },
        {
            "time": "14.12.2020 03:54",
            "open": "2.342",
            "high": "2.342",
            "low": "2.342",
            "close": "2.344"
        },
        {
            "time": "14.12.2020 03:57",
            "open": "2.344",
            "high": "2.344",
            "low": "2.344",
            "close": "2.344"
        },
        {
            "time": "14.12.2020 03:58",
            "open": "2.344",
            "high": "2.346",
            "low": "2.344",
            "close": "2.346"
        },
        {
            "time": "14.12.2020 04:09",
            "open": "2.346",
            "high": "2.346",
            "low": "2.346",
            "close": "2.348"
        },
        {
            "time": "14.12.2020 04:13",
            "open": "2.348",
            "high": "2.348",
            "low": "2.348",
            "close": "2.343"
        },
        {
            "time": "14.12.2020 04:19",
            "open": "2.343",
            "high": "2.343",
            "low": "2.343",
            "close": "2.343"
        },
        {
            "time": "14.12.2020 04:20",
            "open": "2.343",
            "high": "2.343",
            "low": "2.343",
            "close": "2.34"
        },
        {
            "time": "14.12.2020 04:26",
            "open": "2.34",
            "high": "2.34",
            "low": "2.34",
            "close": "2.338"
        },
        {
            "time": "14.12.2020 04:33",
            "open": "2.338",
            "high": "2.338",
            "low": "2.338",
            "close": "2.338"
        },
        {
            "time": "14.12.2020 04:34",
            "open": "2.338",
            "high": "2.338",
            "low": "2.338",
            "close": "2.336"
        },
        {
            "time": "14.12.2020 04:43",
            "open": "2.336",
            "high": "2.336",
            "low": "2.336",
            "close": "2.333"
        },
        {
            "time": "14.12.2020 04:51",
            "open": "2.333",
            "high": "2.333",
            "low": "2.333",
            "close": "2.336"
        },
        {
            "time": "14.12.2020 05:07",
            "open": "2.336",
            "high": "2.336",
            "low": "2.336",
            "close": "2.317"
        },
        {
            "time": "14.12.2020 05:27",
            "open": "2.317",
            "high": "2.317",
            "low": "2.317",
            "close": "2.317"
        },
        {
            "time": "14.12.2020 05:36",
            "open": "2.317",
            "high": "2.317",
            "low": "2.317",
            "close": "2.31"
        },
        {
            "time": "14.12.2020 06:17",
            "open": "2.31",
            "high": "2.31",
            "low": "2.31",
            "close": "2.315"
        },
        {
            "time": "14.12.2020 06:18",
            "open": "2.315",
            "high": "2.315",
            "low": "2.315",
            "close": "2.314"
        },
        {
            "time": "14.12.2020 06:20",
            "open": "2.314",
            "high": "2.314",
            "low": "2.314",
            "close": "2.32"
        },
        {
            "time": "14.12.2020 06:36",
            "open": "2.32",
            "high": "2.321",
            "low": "2.32",
            "close": "2.318"
        },
        {
            "time": "14.12.2020 06:37",
            "open": "2.318",
            "high": "2.318",
            "low": "2.318",
            "close": "2.317"
        },
        {
            "time": "14.12.2020 06:58",
            "open": "2.317",
            "high": "2.317",
            "low": "2.317",
            "close": "2.326"
        },
        {
            "time": "14.12.2020 07:09",
            "open": "2.326",
            "high": "2.326",
            "low": "2.326",
            "close": "2.323"
        },
        {
            "time": "14.12.2020 07:17",
            "open": "2.323",
            "high": "2.323",
            "low": "2.323",
            "close": "2.326"
        },
        {
            "time": "14.12.2020 07:19",
            "open": "2.326",
            "high": "2.326",
            "low": "2.326",
            "close": "2.324"
        },
        {
            "time": "14.12.2020 07:29",
            "open": "2.324",
            "high": "2.324",
            "low": "2.324",
            "close": "2.325"
        },
        {
            "time": "14.12.2020 07:38",
            "open": "2.325",
            "high": "2.325",
            "low": "2.325",
            "close": "2.324"
        },
        {
            "time": "14.12.2020 07:41",
            "open": "2.324",
            "high": "2.325",
            "low": "2.324",
            "close": "2.322"
        },
        {
            "time": "14.12.2020 07:47",
            "open": "2.322",
            "high": "2.323",
            "low": "2.322",
            "close": "2.323"
        },
        {
            "time": "14.12.2020 07:48",
            "open": "2.323",
            "high": "2.323",
            "low": "2.323",
            "close": "2.328"
        },
        {
            "time": "14.12.2020 07:57",
            "open": "2.328",
            "high": "2.328",
            "low": "2.328",
            "close": "2.332"
        },
        {
            "time": "14.12.2020 08:06",
            "open": "2.332",
            "high": "2.332",
            "low": "2.332",
            "close": "2.324"
        },
        {
            "time": "14.12.2020 08:17",
            "open": "2.324",
            "high": "2.324",
            "low": "2.324",
            "close": "2.326"
        },
        {
            "time": "14.12.2020 08:23",
            "open": "2.326",
            "high": "2.326",
            "low": "2.326",
            "close": "2.328"
        },
        {
            "time": "14.12.2020 08:24",
            "open": "2.328",
            "high": "2.328",
            "low": "2.328",
            "close": "2.33"
        },
        {
            "time": "14.12.2020 08:31",
            "open": "2.33",
            "high": "2.335",
            "low": "2.33",
            "close": "2.339"
        },
        {
            "time": "14.12.2020 08:35",
            "open": "2.339",
            "high": "2.339",
            "low": "2.339",
            "close": "2.339"
        },
        {
            "time": "14.12.2020 08:38",
            "open": "2.339",
            "high": "2.339",
            "low": "2.339",
            "close": "2.339"
        },
        {
            "time": "14.12.2020 08:40",
            "open": "2.339",
            "high": "2.34",
            "low": "2.339",
            "close": "2.344"
        },
        {
            "time": "14.12.2020 08:42",
            "open": "2.344",
            "high": "2.344",
            "low": "2.344",
            "close": "2.343"
        },
        {
            "time": "14.12.2020 08:49",
            "open": "2.343",
            "high": "2.343",
            "low": "2.343",
            "close": "2.344"
        },
        {
            "time": "14.12.2020 08:51",
            "open": "2.344",
            "high": "2.344",
            "low": "2.344",
            "close": "2.34"
        },
        {
            "time": "14.12.2020 08:56",
            "open": "2.34",
            "high": "2.34",
            "low": "2.34",
            "close": "2.344"
        },
        {
            "time": "14.12.2020 08:57",
            "open": "2.344",
            "high": "2.344",
            "low": "2.344",
            "close": "2.341"
        },
        {
            "time": "14.12.2020 09:00",
            "open": "2.341",
            "high": "2.341",
            "low": "2.341",
            "close": "2.346"
        },
        {
            "time": "14.12.2020 09:13",
            "open": "2.346",
            "high": "2.346",
            "low": "2.346",
            "close": "2.337"
        },
        {
            "time": "14.12.2020 09:25",
            "open": "2.337",
            "high": "2.338",
            "low": "2.337",
            "close": "2.337"
        },
        {
            "time": "14.12.2020 09:29",
            "open": "2.337",
            "high": "2.337",
            "low": "2.337",
            "close": "2.339"
        },
        {
            "time": "14.12.2020 09:37",
            "open": "2.339",
            "high": "2.339",
            "low": "2.339",
            "close": "2.339"
        },
        {
            "time": "14.12.2020 09:47",
            "open": "2.339",
            "high": "2.339",
            "low": "2.339",
            "close": "2.342"
        },
        {
            "time": "14.12.2020 09:48",
            "open": "2.342",
            "high": "2.342",
            "low": "2.339",
            "close": "2.343"
        },
        {
            "time": "14.12.2020 09:56",
            "open": "2.343",
            "high": "2.343",
            "low": "2.343",
            "close": "2.347"
        },
        {
            "time": "14.12.2020 09:58",
            "open": "2.347",
            "high": "2.348",
            "low": "2.347",
            "close": "2.346"
        },
        {
            "time": "14.12.2020 09:59",
            "open": "2.346",
            "high": "2.348",
            "low": "2.346",
            "close": "2.334"
        },
        {
            "time": "14.12.2020 10:19",
            "open": "2.334",
            "high": "2.334",
            "low": "2.334",
            "close": "2.334"
        },
        {
            "time": "14.12.2020 10:20",
            "open": "2.334",
            "high": "2.334",
            "low": "2.334",
            "close": "2.33"
        },
        {
            "time": "14.12.2020 10:22",
            "open": "2.33",
            "high": "2.33",
            "low": "2.33",
            "close": "2.337"
        },
        {
            "time": "14.12.2020 10:36",
            "open": "2.337",
            "high": "2.337",
            "low": "2.334",
            "close": "2.335"
        },
        {
            "time": "14.12.2020 10:37",
            "open": "2.335",
            "high": "2.335",
            "low": "2.335",
            "close": "2.334"
        },
        {
            "time": "14.12.2020 10:47",
            "open": "2.334",
            "high": "2.334",
            "low": "2.334",
            "close": "2.335"
        },
        {
            "time": "14.12.2020 10:49",
            "open": "2.335",
            "high": "2.335",
            "low": "2.335",
            "close": "2.333"
        },
        {
            "time": "14.12.2020 10:58",
            "open": "2.333",
            "high": "2.333",
            "low": "2.333",
            "close": "2.339"
        },
        {
            "time": "14.12.2020 11:06",
            "open": "2.339",
            "high": "2.339",
            "low": "2.339",
            "close": "2.337"
        },
        {
            "time": "14.12.2020 11:07",
            "open": "2.337",
            "high": "2.337",
            "low": "2.337",
            "close": "2.343"
        },
        {
            "time": "14.12.2020 11:12",
            "open": "2.343",
            "high": "2.345",
            "low": "2.342",
            "close": "2.338"
        },
        {
            "time": "14.12.2020 11:18",
            "open": "2.338",
            "high": "2.338",
            "low": "2.338",
            "close": "2.334"
        },
        {
            "time": "14.12.2020 11:19",
            "open": "2.334",
            "high": "2.334",
            "low": "2.334",
            "close": "2.334"
        },
        {
            "time": "14.12.2020 11:21",
            "open": "2.334",
            "high": "2.334",
            "low": "2.334",
            "close": "2.336"
        },
        {
            "time": "14.12.2020 11:22",
            "open": "2.336",
            "high": "2.336",
            "low": "2.336",
            "close": "2.336"
        },
        {
            "time": "14.12.2020 11:24",
            "open": "2.336",
            "high": "2.336",
            "low": "2.336",
            "close": "2.335"
        },
        {
            "time": "14.12.2020 11:25",
            "open": "2.335",
            "high": "2.335",
            "low": "2.335",
            "close": "2.336"
        },
        {
            "time": "14.12.2020 11:29",
            "open": "2.336",
            "high": "2.336",
            "low": "2.336",
            "close": "2.341"
        },
        {
            "time": "14.12.2020 11:34",
            "open": "2.341",
            "high": "2.341",
            "low": "2.341",
            "close": "2.335"
        },
        {
            "time": "14.12.2020 11:42",
            "open": "2.335",
            "high": "2.335",
            "low": "2.335",
            "close": "2.33"
        },
        {
            "time": "14.12.2020 11:43",
            "open": "2.33",
            "high": "2.33",
            "low": "2.325",
            "close": "2.33"
        },
        {
            "time": "14.12.2020 11:45",
            "open": "2.33",
            "high": "2.33",
            "low": "2.33",
            "close": "2.326"
        },
        {
            "time": "14.12.2020 11:48",
            "open": "2.326",
            "high": "2.326",
            "low": "2.326",
            "close": "2.318"
        },
        {
            "time": "14.12.2020 11:50",
            "open": "2.318",
            "high": "2.318",
            "low": "2.316",
            "close": "2.315"
        },
        {
            "time": "14.12.2020 11:51",
            "open": "2.315",
            "high": "2.317",
            "low": "2.315",
            "close": "2.319"
        },
        {
            "time": "14.12.2020 11:52",
            "open": "2.319",
            "high": "2.319",
            "low": "2.315",
            "close": "2.317"
        },
        {
            "time": "14.12.2020 11:53",
            "open": "2.317",
            "high": "2.317",
            "low": "2.317",
            "close": "2.318"
        },
        {
            "time": "14.12.2020 11:55",
            "open": "2.318",
            "high": "2.318",
            "low": "2.316",
            "close": "2.315"
        },
        {
            "time": "14.12.2020 12:00",
            "open": "2.315",
            "high": "2.316",
            "low": "2.315",
            "close": "2.318"
        },
        {
            "time": "14.12.2020 12:01",
            "open": "2.318",
            "high": "2.318",
            "low": "2.318",
            "close": "2.32"
        },
        {
            "time": "14.12.2020 12:04",
            "open": "2.32",
            "high": "2.32",
            "low": "2.32",
            "close": "2.315"
        },
        {
            "time": "14.12.2020 12:08",
            "open": "2.315",
            "high": "2.315",
            "low": "2.315",
            "close": "2.312"
        },
        {
            "time": "14.12.2020 12:10",
            "open": "2.312",
            "high": "2.312",
            "low": "2.312",
            "close": "2.313"
        },
        {
            "time": "14.12.2020 12:11",
            "open": "2.313",
            "high": "2.313",
            "low": "2.313",
            "close": "2.315"
        },
        {
            "time": "14.12.2020 12:12",
            "open": "2.315",
            "high": "2.315",
            "low": "2.315",
            "close": "2.315"
        },
        {
            "time": "14.12.2020 12:14",
            "open": "2.315",
            "high": "2.315",
            "low": "2.315",
            "close": "2.318"
        },
        {
            "time": "14.12.2020 12:15",
            "open": "2.318",
            "high": "2.318",
            "low": "2.318",
            "close": "2.322"
        },
        {
            "time": "14.12.2020 12:17",
            "open": "2.322",
            "high": "2.322",
            "low": "2.322",
            "close": "2.319"
        },
        {
            "time": "14.12.2020 12:19",
            "open": "2.319",
            "high": "2.319",
            "low": "2.319",
            "close": "2.321"
        },
        {
            "time": "14.12.2020 12:20",
            "open": "2.321",
            "high": "2.321",
            "low": "2.321",
            "close": "2.321"
        },
        {
            "time": "14.12.2020 12:23",
            "open": "2.321",
            "high": "2.321",
            "low": "2.321",
            "close": "2.32"
        },
        {
            "time": "14.12.2020 12:24",
            "open": "2.32",
            "high": "2.32",
            "low": "2.32",
            "close": "2.321"
        },
        {
            "time": "14.12.2020 12:25",
            "open": "2.321",
            "high": "2.321",
            "low": "2.321",
            "close": "2.322"
        },
        {
            "time": "14.12.2020 12:27",
            "open": "2.322",
            "high": "2.322",
            "low": "2.322",
            "close": "2.321"
        },
        {
            "time": "14.12.2020 12:30",
            "open": "2.321",
            "high": "2.321",
            "low": "2.321",
            "close": "2.323"
        },
        {
            "time": "14.12.2020 12:36",
            "open": "2.323",
            "high": "2.323",
            "low": "2.323",
            "close": "2.324"
        },
        {
            "time": "14.12.2020 12:39",
            "open": "2.324",
            "high": "2.325",
            "low": "2.324",
            "close": "2.323"
        },
        {
            "time": "14.12.2020 12:42",
            "open": "2.323",
            "high": "2.323",
            "low": "2.319",
            "close": "2.315"
        },
        {
            "time": "14.12.2020 12:44",
            "open": "2.315",
            "high": "2.317",
            "low": "2.315",
            "close": "2.317"
        },
        {
            "time": "14.12.2020 12:47",
            "open": "2.317",
            "high": "2.317",
            "low": "2.317",
            "close": "2.321"
        },
        {
            "time": "14.12.2020 12:52",
            "open": "2.321",
            "high": "2.321",
            "low": "2.319",
            "close": "2.326"
        },
        {
            "time": "14.12.2020 13:06",
            "open": "2.326",
            "high": "2.329",
            "low": "2.326",
            "close": "2.322"
        },
        {
            "time": "14.12.2020 13:09",
            "open": "2.322",
            "high": "2.323",
            "low": "2.322",
            "close": "2.319"
        },
        {
            "time": "14.12.2020 13:11",
            "open": "2.319",
            "high": "2.319",
            "low": "2.316",
            "close": "2.312"
        },
        {
            "time": "14.12.2020 13:17",
            "open": "2.312",
            "high": "2.312",
            "low": "2.312",
            "close": "2.313"
        },
        {
            "time": "14.12.2020 13:19",
            "open": "2.313",
            "high": "2.313",
            "low": "2.305",
            "close": "2.305"
        },
        {
            "time": "14.12.2020 13:20",
            "open": "2.305",
            "high": "2.305",
            "low": "2.305",
            "close": "2.308"
        },
        {
            "time": "14.12.2020 13:21",
            "open": "2.308",
            "high": "2.308",
            "low": "2.308",
            "close": "2.308"
        },
        {
            "time": "14.12.2020 13:23",
            "open": "2.308",
            "high": "2.308",
            "low": "2.308",
            "close": "2.314"
        },
        {
            "time": "14.12.2020 13:27",
            "open": "2.314",
            "high": "2.314",
            "low": "2.314",
            "close": "2.318"
        },
        {
            "time": "14.12.2020 13:28",
            "open": "2.318",
            "high": "2.318",
            "low": "2.318",
            "close": "2.317"
        },
        {
            "time": "14.12.2020 13:30",
            "open": "2.317",
            "high": "2.317",
            "low": "2.317",
            "close": "2.319"
        },
        {
            "time": "14.12.2020 13:31",
            "open": "2.319",
            "high": "2.319",
            "low": "2.319",
            "close": "2.316"
        },
        {
            "time": "14.12.2020 13:36",
            "open": "2.316",
            "high": "2.316",
            "low": "2.316",
            "close": "2.316"
        },
        {
            "time": "14.12.2020 13:50",
            "open": "2.316",
            "high": "2.316",
            "low": "2.316",
            "close": "2.312"
        },
        {
            "time": "14.12.2020 13:51",
            "open": "2.312",
            "high": "2.312",
            "low": "2.312",
            "close": "2.317"
        },
        {
            "time": "14.12.2020 13:57",
            "open": "2.317",
            "high": "2.317",
            "low": "2.317",
            "close": "2.317"
        },
        {
            "time": "14.12.2020 13:58",
            "open": "2.317",
            "high": "2.317",
            "low": "2.317",
            "close": "2.315"
        },
        {
            "time": "14.12.2020 14:02",
            "open": "2.315",
            "high": "2.315",
            "low": "2.315",
            "close": "2.319"
        },
        {
            "time": "14.12.2020 14:03",
            "open": "2.319",
            "high": "2.319",
            "low": "2.319",
            "close": "2.319"
        },
        {
            "time": "14.12.2020 14:04",
            "open": "2.319",
            "high": "2.319",
            "low": "2.319",
            "close": "2.317"
        },
        {
            "time": "14.12.2020 14:08",
            "open": "2.317",
            "high": "2.317",
            "low": "2.317",
            "close": "2.316"
        },
        {
            "time": "14.12.2020 14:14",
            "open": "2.316",
            "high": "2.317",
            "low": "2.316",
            "close": "2.312"
        },
        {
            "time": "14.12.2020 14:19",
            "open": "2.312",
            "high": "2.312",
            "low": "2.312",
            "close": "2.309"
        },
        {
            "time": "14.12.2020 14:20",
            "open": "2.309",
            "high": "2.317",
            "low": "2.309",
            "close": "2.312"
        },
        {
            "time": "14.12.2020 14:21",
            "open": "2.312",
            "high": "2.312",
            "low": "2.312",
            "close": "2.311"
        },
        {
            "time": "14.12.2020 14:22",
            "open": "2.311",
            "high": "2.311",
            "low": "2.311",
            "close": "2.318"
        },
        {
            "time": "14.12.2020 14:29",
            "open": "2.318",
            "high": "2.318",
            "low": "2.318",
            "close": "2.322"
        }
    ]
}